{
"meta":{"test_sets":[],"test_metrics":[],"learn_metrics":[{"best_value":"Min","name":"RMSE"}],"launch_mode":"Train","parameters":"","iteration_count":1000,"learn_sets":["learn"],"name":"experiment"},
"iterations":[
{"learn":[14.59871775],"iteration":0,"passed_time":0.1115590855,"remaining_time":111.4475264},
{"learn":[14.22518863],"iteration":1,"passed_time":0.1131479648,"remaining_time":56.46083443},
{"learn":[13.8866124],"iteration":2,"passed_time":0.1163116477,"remaining_time":38.65423758},
{"learn":[13.52356875],"iteration":3,"passed_time":0.1173615398,"remaining_time":29.22302341},
{"learn":[13.18870211],"iteration":4,"passed_time":0.1189020545,"remaining_time":23.66150885},
{"learn":[12.9124226],"iteration":5,"passed_time":0.1198727244,"remaining_time":19.85891468},
{"learn":[12.60003351],"iteration":6,"passed_time":0.1209165317,"remaining_time":17.15287371},
{"learn":[12.32990573],"iteration":7,"passed_time":0.1236810598,"remaining_time":15.33645141},
{"learn":[12.0660619],"iteration":8,"passed_time":0.125062946,"remaining_time":13.77081994},
{"learn":[11.77309809],"iteration":9,"passed_time":0.1262979269,"remaining_time":12.50349476},
{"learn":[11.49227636],"iteration":10,"passed_time":0.1282310395,"remaining_time":11.52913619},
{"learn":[11.26264833],"iteration":11,"passed_time":0.1301117089,"remaining_time":10.7125307},
{"learn":[11.04260393],"iteration":12,"passed_time":0.1314034978,"remaining_time":9.976557868},
{"learn":[10.79916926],"iteration":13,"passed_time":0.1327866652,"remaining_time":9.351975134},
{"learn":[10.5541002],"iteration":14,"passed_time":0.1337373542,"remaining_time":8.78208626},
{"learn":[10.31918115],"iteration":15,"passed_time":0.13484261,"remaining_time":8.292820512},
{"learn":[10.10004441],"iteration":16,"passed_time":0.135878272,"remaining_time":7.856961259},
{"learn":[9.894556723],"iteration":17,"passed_time":0.1370420369,"remaining_time":7.476404457},
{"learn":[9.690174082],"iteration":18,"passed_time":0.1381176205,"remaining_time":7.131230828},
{"learn":[9.506034866],"iteration":19,"passed_time":0.1390994545,"remaining_time":6.815873272},
{"learn":[9.338524633],"iteration":20,"passed_time":0.1402904843,"remaining_time":6.540208767},
{"learn":[9.170203312],"iteration":21,"passed_time":0.1414806299,"remaining_time":6.289457092},
{"learn":[9.010299969],"iteration":22,"passed_time":0.1424807846,"remaining_time":6.052335938},
{"learn":[8.843866678],"iteration":23,"passed_time":0.1449607282,"remaining_time":5.895069614},
{"learn":[8.690548059],"iteration":24,"passed_time":0.1463085748,"remaining_time":5.706034416},
{"learn":[8.555307687],"iteration":25,"passed_time":0.1473140785,"remaining_time":5.518612016},
{"learn":[8.413851302],"iteration":26,"passed_time":0.1482694188,"remaining_time":5.343190537},
{"learn":[8.29256019],"iteration":27,"passed_time":0.1491600776,"remaining_time":5.177985551},
{"learn":[8.162193833],"iteration":28,"passed_time":0.1501484546,"remaining_time":5.027384461},
{"learn":[8.040736294],"iteration":29,"passed_time":0.151407106,"remaining_time":4.895496426},
{"learn":[7.921220278],"iteration":30,"passed_time":0.1525919585,"remaining_time":4.769729282},
{"learn":[7.809589039],"iteration":31,"passed_time":0.1536107064,"remaining_time":4.646723868},
{"learn":[7.699675801],"iteration":32,"passed_time":0.1546194834,"remaining_time":4.530819406},
{"learn":[7.60645267],"iteration":33,"passed_time":0.1555517154,"remaining_time":4.419498738},
{"learn":[7.498880302],"iteration":34,"passed_time":0.1566479945,"remaining_time":4.31900899},
{"learn":[7.401158744],"iteration":35,"passed_time":0.1575600925,"remaining_time":4.219109145},
{"learn":[7.306431077],"iteration":36,"passed_time":0.1589054712,"remaining_time":4.135836993},
{"learn":[7.223863468],"iteration":37,"passed_time":0.1600242207,"remaining_time":4.051139482},
{"learn":[7.143477682],"iteration":38,"passed_time":0.1611374782,"remaining_time":3.970592732},
{"learn":[7.062817131],"iteration":39,"passed_time":0.1620278758,"remaining_time":3.888669019},
{"learn":[6.990793435],"iteration":40,"passed_time":0.1628644574,"remaining_time":3.809439381},
{"learn":[6.931862224],"iteration":41,"passed_time":0.1637935926,"remaining_time":3.73605385},
{"learn":[6.858296558],"iteration":42,"passed_time":0.1649177429,"remaining_time":3.670378604},
{"learn":[6.786268161],"iteration":43,"passed_time":0.1658040968,"remaining_time":3.602470831},
{"learn":[6.717118549],"iteration":44,"passed_time":0.1667603751,"remaining_time":3.539025739},
{"learn":[6.652948106],"iteration":45,"passed_time":0.1676166454,"remaining_time":3.476223472},
{"learn":[6.589686076],"iteration":46,"passed_time":0.1685196446,"remaining_time":3.417004709},
{"learn":[6.531283097],"iteration":47,"passed_time":0.1693476506,"remaining_time":3.358728403},
{"learn":[6.471368031],"iteration":48,"passed_time":0.1702612082,"remaining_time":3.304457327},
{"learn":[6.416481395],"iteration":49,"passed_time":0.1720485628,"remaining_time":3.268922694},
{"learn":[6.369870822],"iteration":50,"passed_time":0.1732279968,"remaining_time":3.223399392},
{"learn":[6.325678067],"iteration":51,"passed_time":0.1746271782,"remaining_time":3.183587788},
{"learn":[6.275766122],"iteration":52,"passed_time":0.1755963021,"remaining_time":3.137541474},
{"learn":[6.224773967],"iteration":53,"passed_time":0.1764499116,"remaining_time":3.091141043},
{"learn":[6.182249254],"iteration":54,"passed_time":0.1774211626,"remaining_time":3.048418157},
{"learn":[6.139904173],"iteration":55,"passed_time":0.1783886114,"remaining_time":3.007122307},
{"learn":[6.100525536],"iteration":56,"passed_time":0.1794933335,"remaining_time":2.969512517},
{"learn":[6.062568564],"iteration":57,"passed_time":0.1809513141,"remaining_time":2.93889893},
{"learn":[6.030559288],"iteration":58,"passed_time":0.1821045531,"remaining_time":2.904413296},
{"learn":[5.997931376],"iteration":59,"passed_time":0.1831895953,"remaining_time":2.869970326},
{"learn":[5.964103835],"iteration":60,"passed_time":0.1842729295,"remaining_time":2.836594767},
{"learn":[5.933729724],"iteration":61,"passed_time":0.1853077002,"remaining_time":2.803526174},
{"learn":[5.901932711],"iteration":62,"passed_time":0.1873345929,"remaining_time":2.786230374},
{"learn":[5.873727795],"iteration":63,"passed_time":0.1889113304,"remaining_time":2.762828207},
{"learn":[5.846485734],"iteration":64,"passed_time":0.1902945717,"remaining_time":2.737314224},
{"learn":[5.820630862],"iteration":65,"passed_time":0.1914299356,"remaining_time":2.709023635},
{"learn":[5.793646238],"iteration":66,"passed_time":0.1923629248,"remaining_time":2.678725506},
{"learn":[5.765388646],"iteration":67,"passed_time":0.1944191598,"remaining_time":2.664686131},
{"learn":[5.747073912],"iteration":68,"passed_time":0.1957461019,"remaining_time":2.641153926},
{"learn":[5.722315217],"iteration":69,"passed_time":0.1970787086,"remaining_time":2.618331414},
{"learn":[5.699970599],"iteration":70,"passed_time":0.1982850261,"remaining_time":2.59446182},
{"learn":[5.682732647],"iteration":71,"passed_time":0.1998926955,"remaining_time":2.576394742},
{"learn":[5.663525791],"iteration":72,"passed_time":0.202308824,"remaining_time":2.569044929},
{"learn":[5.642381613],"iteration":73,"passed_time":0.2036905004,"remaining_time":2.54888383},
{"learn":[5.621404779],"iteration":74,"passed_time":0.2050169961,"remaining_time":2.528542952},
{"learn":[5.602460129],"iteration":75,"passed_time":0.2060931778,"remaining_time":2.505659161},
{"learn":[5.587337574],"iteration":76,"passed_time":0.2071739717,"remaining_time":2.48339709},
{"learn":[5.572393026],"iteration":77,"passed_time":0.2092797736,"remaining_time":2.473794247},
{"learn":[5.558425806],"iteration":78,"passed_time":0.2109403508,"remaining_time":2.459190672},
{"learn":[5.541518902],"iteration":79,"passed_time":0.2124757239,"remaining_time":2.443470825},
{"learn":[5.526157283],"iteration":80,"passed_time":0.213431725,"remaining_time":2.421527842},
{"learn":[5.511746977],"iteration":81,"passed_time":0.2145286189,"remaining_time":2.40167405},
{"learn":[5.504975022],"iteration":82,"passed_time":0.2150931007,"remaining_time":2.37639004},
{"learn":[5.493980522],"iteration":83,"passed_time":0.2165878015,"remaining_time":2.361838407},
{"learn":[5.480745463],"iteration":84,"passed_time":0.218504135,"remaining_time":2.352132747},
{"learn":[5.464052013],"iteration":85,"passed_time":0.2202131736,"remaining_time":2.340405124},
{"learn":[5.449143727],"iteration":86,"passed_time":0.221965182,"remaining_time":2.329358749},
{"learn":[5.438255432],"iteration":87,"passed_time":0.2228411149,"remaining_time":2.309444281},
{"learn":[5.425927931],"iteration":88,"passed_time":0.2238544447,"remaining_time":2.291364035},
{"learn":[5.412331217],"iteration":89,"passed_time":0.224827036,"remaining_time":2.273251141},
{"learn":[5.400691499],"iteration":90,"passed_time":0.2257823775,"remaining_time":2.25534265},
{"learn":[5.391618744],"iteration":91,"passed_time":0.2267745715,"remaining_time":2.238166423},
{"learn":[5.380766572],"iteration":92,"passed_time":0.2277457614,"remaining_time":2.221133393},
{"learn":[5.372207183],"iteration":93,"passed_time":0.2287501861,"remaining_time":2.204762432},
{"learn":[5.362918837],"iteration":94,"passed_time":0.2298926302,"remaining_time":2.190029793},
{"learn":[5.348292324],"iteration":95,"passed_time":0.2308965155,"remaining_time":2.174275521},
{"learn":[5.339772295],"iteration":96,"passed_time":0.2321391646,"remaining_time":2.1610481},
{"learn":[5.331515983],"iteration":97,"passed_time":0.2336350378,"remaining_time":2.15039596},
{"learn":[5.323861644],"iteration":98,"passed_time":0.2347290406,"remaining_time":2.136271369},
{"learn":[5.313277281],"iteration":99,"passed_time":0.2358993211,"remaining_time":2.12309389},
{"learn":[5.30685627],"iteration":100,"passed_time":0.2371155404,"remaining_time":2.110563077},
{"learn":[5.29652059],"iteration":101,"passed_time":0.2382884994,"remaining_time":2.097873259},
{"learn":[5.288350766],"iteration":102,"passed_time":0.2394736428,"remaining_time":2.085513181},
{"learn":[5.27993346],"iteration":103,"passed_time":0.2406897745,"remaining_time":2.073634981},
{"learn":[5.271789139],"iteration":104,"passed_time":0.2417823973,"remaining_time":2.060907101},
{"learn":[5.262684686],"iteration":105,"passed_time":0.2428537122,"remaining_time":2.048219045},
{"learn":[5.251619772],"iteration":106,"passed_time":0.2446015463,"remaining_time":2.041394214},
{"learn":[5.241012171],"iteration":107,"passed_time":0.2455562774,"remaining_time":2.028112958},
{"learn":[5.232684032],"iteration":108,"passed_time":0.2475231026,"remaining_time":2.023331049},
{"learn":[5.224267141],"iteration":109,"passed_time":0.248522931,"remaining_time":2.010776442},
{"learn":[5.216324968],"iteration":110,"passed_time":0.2497394296,"remaining_time":2.000165342},
{"learn":[5.211102527],"iteration":111,"passed_time":0.2507618961,"remaining_time":1.988183605},
{"learn":[5.206364257],"iteration":112,"passed_time":0.2517103226,"remaining_time":1.975814656},
{"learn":[5.196937641],"iteration":113,"passed_time":0.2529960049,"remaining_time":1.966267196},
{"learn":[5.190746047],"iteration":114,"passed_time":0.254248,"remaining_time":1.956604174},
{"learn":[5.181885213],"iteration":115,"passed_time":0.2552882648,"remaining_time":1.945472639},
{"learn":[5.178293568],"iteration":116,"passed_time":0.2561810435,"remaining_time":1.933400525},
{"learn":[5.170991438],"iteration":117,"passed_time":0.2571910514,"remaining_time":1.92239413},
{"learn":[5.166257212],"iteration":118,"passed_time":0.2580508369,"remaining_time":1.910443591},
{"learn":[5.161421246],"iteration":119,"passed_time":0.2589215627,"remaining_time":1.898758126},
{"learn":[5.158223542],"iteration":120,"passed_time":0.2598893146,"remaining_time":1.88795626},
{"learn":[5.15470988],"iteration":121,"passed_time":0.2606206058,"remaining_time":1.875613868},
{"learn":[5.146388143],"iteration":122,"passed_time":0.2624916768,"remaining_time":1.871586996},
{"learn":[5.139529364],"iteration":123,"passed_time":0.2636352056,"remaining_time":1.862455162},
{"learn":[5.134276023],"iteration":124,"passed_time":0.2647768596,"remaining_time":1.853438018},
{"learn":[5.128536065],"iteration":125,"passed_time":0.2662104364,"remaining_time":1.846570805},
{"learn":[5.123300353],"iteration":126,"passed_time":0.2669744315,"remaining_time":1.835186447},
{"learn":[5.116200518],"iteration":127,"passed_time":0.2680224304,"remaining_time":1.825902807},
{"learn":[5.108728704],"iteration":128,"passed_time":0.269635329,"remaining_time":1.82056102},
{"learn":[5.104075866],"iteration":129,"passed_time":0.2708416308,"remaining_time":1.81255553},
{"learn":[5.100317606],"iteration":130,"passed_time":0.2719543209,"remaining_time":1.804032862},
{"learn":[5.095814182],"iteration":131,"passed_time":0.2729621732,"remaining_time":1.794933078},
{"learn":[5.092146915],"iteration":132,"passed_time":0.2740951732,"remaining_time":1.786770791},
{"learn":[5.085258329],"iteration":133,"passed_time":0.2751496684,"remaining_time":1.778206066},
{"learn":[5.079219421],"iteration":134,"passed_time":0.276160628,"remaining_time":1.769473653},
{"learn":[5.076476829],"iteration":135,"passed_time":0.2778238772,"remaining_time":1.764998749},
{"learn":[5.072133867],"iteration":136,"passed_time":0.2789740547,"remaining_time":1.757332914},
{"learn":[5.067031564],"iteration":137,"passed_time":0.2799873648,"remaining_time":1.748906583},
{"learn":[5.061358312],"iteration":138,"passed_time":0.2814900783,"remaining_time":1.743618399},
{"learn":[5.056759124],"iteration":139,"passed_time":0.2825563617,"remaining_time":1.735703365},
{"learn":[5.050254],"iteration":140,"passed_time":0.2836329251,"remaining_time":1.727948104},
{"learn":[5.048376474],"iteration":141,"passed_time":0.2843456425,"remaining_time":1.718088459},
{"learn":[5.042603751],"iteration":142,"passed_time":0.2858250166,"remaining_time":1.712951323},
{"learn":[5.037477349],"iteration":143,"passed_time":0.287013136,"remaining_time":1.706133642},
{"learn":[5.03230489],"iteration":144,"passed_time":0.2881118468,"remaining_time":1.698866407},
{"learn":[5.025976187],"iteration":145,"passed_time":0.2892663239,"remaining_time":1.692009867},
{"learn":[5.01952451],"iteration":146,"passed_time":0.2904500893,"remaining_time":1.685400858},
{"learn":[5.017569424],"iteration":147,"passed_time":0.2920278917,"remaining_time":1.681133539},
{"learn":[5.008962367],"iteration":148,"passed_time":0.2939998146,"remaining_time":1.679153304},
{"learn":[5.003880266],"iteration":149,"passed_time":0.295274904,"remaining_time":1.673224456},
{"learn":[4.996387564],"iteration":150,"passed_time":0.2963345528,"remaining_time":1.666145929},
{"learn":[4.993361683],"iteration":151,"passed_time":0.2974203517,"remaining_time":1.659292489},
{"learn":[4.99005752],"iteration":152,"passed_time":0.2984673085,"remaining_time":1.652299414},
{"learn":[4.986908764],"iteration":153,"passed_time":0.3000389369,"remaining_time":1.648265848},
{"learn":[4.985207175],"iteration":154,"passed_time":0.3010570812,"remaining_time":1.641246669},
{"learn":[4.979003494],"iteration":155,"passed_time":0.3024727194,"remaining_time":1.636454969},
{"learn":[4.973142217],"iteration":156,"passed_time":0.3035799287,"remaining_time":1.63005019},
{"learn":[4.967056696],"iteration":157,"passed_time":0.3046242227,"remaining_time":1.623377187},
{"learn":[4.961460696],"iteration":158,"passed_time":0.3059088473,"remaining_time":1.618046167},
{"learn":[4.954240363],"iteration":159,"passed_time":0.3083796092,"remaining_time":1.618992948},
{"learn":[4.952320707],"iteration":160,"passed_time":0.3093599145,"remaining_time":1.612130238},
{"learn":[4.948337777],"iteration":161,"passed_time":0.3108384616,"remaining_time":1.607917474},
{"learn":[4.943228639],"iteration":162,"passed_time":0.312327932,"remaining_time":1.60379435},
{"learn":[4.938545759],"iteration":163,"passed_time":0.3135665346,"remaining_time":1.59842453},
{"learn":[4.935330572],"iteration":164,"passed_time":0.3151773475,"remaining_time":1.594988395},
{"learn":[4.932051543],"iteration":165,"passed_time":0.3167090443,"remaining_time":1.591176765},
{"learn":[4.928964153],"iteration":166,"passed_time":0.3177685175,"remaining_time":1.585036977},
{"learn":[4.922860227],"iteration":167,"passed_time":0.319110129,"remaining_time":1.580354924},
{"learn":[4.917668772],"iteration":168,"passed_time":0.3204745031,"remaining_time":1.575824332},
{"learn":[4.910365386],"iteration":169,"passed_time":0.3217438822,"remaining_time":1.570867189},
{"learn":[4.906457206],"iteration":170,"passed_time":0.3234235087,"remaining_time":1.567942039},
{"learn":[4.901996508],"iteration":171,"passed_time":0.3248430933,"remaining_time":1.563779542},
{"learn":[4.896816173],"iteration":172,"passed_time":0.3261915616,"remaining_time":1.559308794},
{"learn":[4.891123132],"iteration":173,"passed_time":0.3275532809,"remaining_time":1.554936839},
{"learn":[4.887630202],"iteration":174,"passed_time":0.3286881573,"remaining_time":1.549529884},
{"learn":[4.885259712],"iteration":175,"passed_time":0.3300693973,"remaining_time":1.545324906},
{"learn":[4.880659728],"iteration":176,"passed_time":0.3316361055,"remaining_time":1.542014208},
{"learn":[4.877299723],"iteration":177,"passed_time":0.3327667048,"remaining_time":1.536709165},
{"learn":[4.874038772],"iteration":178,"passed_time":0.3340323729,"remaining_time":1.532070269},
{"learn":[4.86943698],"iteration":179,"passed_time":0.3351302145,"remaining_time":1.52670431},
{"learn":[4.861268711],"iteration":180,"passed_time":0.3362677907,"remaining_time":1.521565307},
{"learn":[4.858673056],"iteration":181,"passed_time":0.3387002245,"remaining_time":1.52229002},
{"learn":[4.854036207],"iteration":182,"passed_time":0.3408439044,"remaining_time":1.521691092},
{"learn":[4.85130244],"iteration":183,"passed_time":0.3419008028,"remaining_time":1.516255734},
{"learn":[4.847510084],"iteration":184,"passed_time":0.3428884033,"remaining_time":1.510562426},
{"learn":[4.845691673],"iteration":185,"passed_time":0.3438538187,"remaining_time":1.504822626},
{"learn":[4.842058646],"iteration":186,"passed_time":0.3456270409,"remaining_time":1.502645905},
{"learn":[4.838623675],"iteration":187,"passed_time":0.3469339275,"remaining_time":1.498459304},
{"learn":[4.834602161],"iteration":188,"passed_time":0.3482400356,"remaining_time":1.494299835},
{"learn":[4.830858976],"iteration":189,"passed_time":0.3491156952,"remaining_time":1.488335332},
{"learn":[4.827590511],"iteration":190,"passed_time":0.3499866138,"remaining_time":1.482404035},
{"learn":[4.822246226],"iteration":191,"passed_time":0.3509968275,"remaining_time":1.477111649},
{"learn":[4.816686395],"iteration":192,"passed_time":0.3531232738,"remaining_time":1.476530995},
{"learn":[4.814797121],"iteration":193,"passed_time":0.3554548878,"remaining_time":1.476786802},
{"learn":[4.811639392],"iteration":194,"passed_time":0.3566896597,"remaining_time":1.472488082},
{"learn":[4.804813432],"iteration":195,"passed_time":0.3578708174,"remaining_time":1.4680007},
{"learn":[4.80251613],"iteration":196,"passed_time":0.3594398251,"remaining_time":1.465127815},
{"learn":[4.800087884],"iteration":197,"passed_time":0.360994934,"remaining_time":1.462211803},
{"learn":[4.794773135],"iteration":198,"passed_time":0.3623516105,"remaining_time":1.458510754},
{"learn":[4.791664833],"iteration":199,"passed_time":0.3641509623,"remaining_time":1.456603849},
{"learn":[4.785989873],"iteration":200,"passed_time":0.3662556076,"remaining_time":1.455911595},
{"learn":[4.782387142],"iteration":201,"passed_time":0.368842822,"remaining_time":1.457111742},
{"learn":[4.778623704],"iteration":202,"passed_time":0.3708971817,"remaining_time":1.456182531},
{"learn":[4.775772178],"iteration":203,"passed_time":0.3720861904,"remaining_time":1.451865723},
{"learn":[4.77023101],"iteration":204,"passed_time":0.3734093699,"remaining_time":1.448099751},
{"learn":[4.764496689],"iteration":205,"passed_time":0.3746061107,"remaining_time":1.443870155},
{"learn":[4.763138716],"iteration":206,"passed_time":0.3760957527,"remaining_time":1.440791942},
{"learn":[4.758053283],"iteration":207,"passed_time":0.377504168,"remaining_time":1.437419717},
{"learn":[4.755063788],"iteration":208,"passed_time":0.3786440144,"remaining_time":1.433049834},
{"learn":[4.752465267],"iteration":209,"passed_time":0.3798036709,"remaining_time":1.428785238},
{"learn":[4.748067377],"iteration":210,"passed_time":0.3808772239,"remaining_time":1.424228102},
{"learn":[4.744163298],"iteration":211,"passed_time":0.3819059178,"remaining_time":1.419537091},
{"learn":[4.736670896],"iteration":212,"passed_time":0.3835202009,"remaining_time":1.417044123},
{"learn":[4.73349255],"iteration":213,"passed_time":0.3850449082,"remaining_time":1.414230364},
{"learn":[4.731864595],"iteration":214,"passed_time":0.3860443271,"remaining_time":1.409510683},
{"learn":[4.728398311],"iteration":215,"passed_time":0.3869701826,"remaining_time":1.404558441},
{"learn":[4.723865975],"iteration":216,"passed_time":0.388119613,"remaining_time":1.400450032},
{"learn":[4.723483365],"iteration":217,"passed_time":0.38927193,"remaining_time":1.396379125},
{"learn":[4.72095416],"iteration":218,"passed_time":0.3908538223,"remaining_time":1.393866827},
{"learn":[4.716173382],"iteration":219,"passed_time":0.3923411745,"remaining_time":1.3910278},
{"learn":[4.710563974],"iteration":220,"passed_time":0.3934920648,"remaining_time":1.387015016},
{"learn":[4.707160263],"iteration":221,"passed_time":0.3946593541,"remaining_time":1.383085484},
{"learn":[4.70408351],"iteration":222,"passed_time":0.395897239,"remaining_time":1.379426703},
{"learn":[4.702501831],"iteration":223,"passed_time":0.3970250641,"remaining_time":1.375408258},
{"learn":[4.700269738],"iteration":224,"passed_time":0.3993174482,"remaining_time":1.375426766},
{"learn":[4.695346302],"iteration":225,"passed_time":0.4008655873,"remaining_time":1.372875949},
{"learn":[4.689769299],"iteration":226,"passed_time":0.4017032885,"remaining_time":1.367914722},
{"learn":[4.687919514],"iteration":227,"passed_time":0.4027557482,"remaining_time":1.363716832},
{"learn":[4.682982074],"iteration":228,"passed_time":0.4038681995,"remaining_time":1.359748392},
{"learn":[4.679578702],"iteration":229,"passed_time":0.4047638259,"remaining_time":1.355078895},
{"learn":[4.675751423],"iteration":230,"passed_time":0.405975236,"remaining_time":1.351493318},
{"learn":[4.672710726],"iteration":231,"passed_time":0.4074737993,"remaining_time":1.348878784},
{"learn":[4.6690533],"iteration":232,"passed_time":0.408645156,"remaining_time":1.345196715},
{"learn":[4.667595702],"iteration":233,"passed_time":0.4100786162,"remaining_time":1.342394103},
{"learn":[4.664241291],"iteration":234,"passed_time":0.4112289282,"remaining_time":1.338681405},
{"learn":[4.662246999],"iteration":235,"passed_time":0.412333975,"remaining_time":1.334843885},
{"learn":[4.658668443],"iteration":236,"passed_time":0.414183923,"remaining_time":1.333427566},
{"learn":[4.658017572],"iteration":237,"passed_time":0.415657484,"remaining_time":1.330802533},
{"learn":[4.657656705],"iteration":238,"passed_time":0.4173080729,"remaining_time":1.32875081},
{"learn":[4.653242871],"iteration":239,"passed_time":0.4184057931,"remaining_time":1.324951678},
{"learn":[4.6507302],"iteration":240,"passed_time":0.4194549293,"remaining_time":1.321021956},
{"learn":[4.647671336],"iteration":241,"passed_time":0.4212179535,"remaining_time":1.319352102},
{"learn":[4.645506007],"iteration":242,"passed_time":0.4224987655,"remaining_time":1.316179282},
{"learn":[4.641297906],"iteration":243,"passed_time":0.42368198,"remaining_time":1.312719577},
{"learn":[4.63798107],"iteration":244,"passed_time":0.4248048266,"remaining_time":1.309092425},
{"learn":[4.635062318],"iteration":245,"passed_time":0.4257896912,"remaining_time":1.305062712},
{"learn":[4.631606017],"iteration":246,"passed_time":0.4268191085,"remaining_time":1.301193477},
{"learn":[4.630215494],"iteration":247,"passed_time":0.4287988556,"remaining_time":1.300228788},
{"learn":[4.62729814],"iteration":248,"passed_time":0.4330921222,"remaining_time":1.30623367},
{"learn":[4.624691756],"iteration":249,"passed_time":0.4350282051,"remaining_time":1.305084615},
{"learn":[4.621840053],"iteration":250,"passed_time":0.4380436275,"remaining_time":1.307150107},
{"learn":[4.619602091],"iteration":251,"passed_time":0.4393496986,"remaining_time":1.304101486},
{"learn":[4.613584029],"iteration":252,"passed_time":0.4409967957,"remaining_time":1.302073543},
{"learn":[4.6119388],"iteration":253,"passed_time":0.4423255093,"remaining_time":1.299113504},
{"learn":[4.60870702],"iteration":254,"passed_time":0.4443397848,"remaining_time":1.298169175},
{"learn":[4.604771557],"iteration":255,"passed_time":0.4457626925,"remaining_time":1.295497825},
{"learn":[4.604231277],"iteration":256,"passed_time":0.4471737289,"remaining_time":1.29280187},
{"learn":[4.600750354],"iteration":257,"passed_time":0.4483095505,"remaining_time":1.289324366},
{"learn":[4.596488253],"iteration":258,"passed_time":0.4492998267,"remaining_time":1.285448539},
{"learn":[4.59470784],"iteration":259,"passed_time":0.4506176744,"remaining_time":1.282527227},
{"learn":[4.588818005],"iteration":260,"passed_time":0.4520086153,"remaining_time":1.27982516},
{"learn":[4.585054174],"iteration":261,"passed_time":0.4533237898,"remaining_time":1.276919683},
{"learn":[4.581471435],"iteration":262,"passed_time":0.4545271656,"remaining_time":1.273713008},
{"learn":[4.577555199],"iteration":263,"passed_time":0.4557457825,"remaining_time":1.270564},
{"learn":[4.57457145],"iteration":264,"passed_time":0.4569312852,"remaining_time":1.267337716},
{"learn":[4.573029224],"iteration":265,"passed_time":0.4592314733,"remaining_time":1.267202637},
{"learn":[4.571326203],"iteration":266,"passed_time":0.461509641,"remaining_time":1.266990887},
{"learn":[4.571019224],"iteration":267,"passed_time":0.4626692665,"remaining_time":1.263708594},
{"learn":[4.565766631],"iteration":268,"passed_time":0.4638725844,"remaining_time":1.260560815},
{"learn":[4.563383471],"iteration":269,"passed_time":0.4654634317,"remaining_time":1.258475204},
{"learn":[4.558165805],"iteration":270,"passed_time":0.4673501755,"remaining_time":1.257189217},
{"learn":[4.55629209],"iteration":271,"passed_time":0.4685428738,"remaining_time":1.254041221},
{"learn":[4.549383848],"iteration":272,"passed_time":0.4698478024,"remaining_time":1.251206419},
{"learn":[4.546227503],"iteration":273,"passed_time":0.4716535195,"remaining_time":1.24970969},
{"learn":[4.540620977],"iteration":274,"passed_time":0.4744387791,"remaining_time":1.250793145},
{"learn":[4.532898237],"iteration":275,"passed_time":0.4769012037,"remaining_time":1.251001708},
{"learn":[4.529757367],"iteration":276,"passed_time":0.4785582963,"remaining_time":1.249088983},
{"learn":[4.52579294],"iteration":277,"passed_time":0.4807893263,"remaining_time":1.248668682},
{"learn":[4.521572155],"iteration":278,"passed_time":0.4834129478,"remaining_time":1.249249948},
{"learn":[4.518818099],"iteration":279,"passed_time":0.4852353255,"remaining_time":1.24774798},
{"learn":[4.514012334],"iteration":280,"passed_time":0.4873569147,"remaining_time":1.24700933},
{"learn":[4.508331416],"iteration":281,"passed_time":0.4897607345,"remaining_time":1.246979459},
{"learn":[4.506038537],"iteration":282,"passed_time":0.4921414128,"remaining_time":1.24687418},
{"learn":[4.505805643],"iteration":283,"passed_time":0.4934309527,"remaining_time":1.244001979},
{"learn":[4.501550352],"iteration":284,"passed_time":0.4951528216,"remaining_time":1.2422255},
{"learn":[4.494692643],"iteration":285,"passed_time":0.4971203006,"remaining_time":1.241062569},
{"learn":[4.489330245],"iteration":286,"passed_time":0.4983503674,"remaining_time":1.238062063},
{"learn":[4.484826955],"iteration":287,"passed_time":0.499849372,"remaining_time":1.235738725},
{"learn":[4.478285428],"iteration":288,"passed_time":0.5009959667,"remaining_time":1.232554091},
{"learn":[4.475311671],"iteration":289,"passed_time":0.503365816,"remaining_time":1.232378377},
{"learn":[4.471581298],"iteration":290,"passed_time":0.5056231363,"remaining_time":1.231913415},
{"learn":[4.469164956],"iteration":291,"passed_time":0.5072570101,"remaining_time":1.229924531},
{"learn":[4.462068024],"iteration":292,"passed_time":0.5089818018,"remaining_time":1.228157454},
{"learn":[4.458540976],"iteration":293,"passed_time":0.5106063356,"remaining_time":1.226149908},
{"learn":[4.455757458],"iteration":294,"passed_time":0.5119020307,"remaining_time":1.22335909},
{"learn":[4.453027414],"iteration":295,"passed_time":0.5129943657,"remaining_time":1.220094708},
{"learn":[4.450659338],"iteration":296,"passed_time":0.5145770931,"remaining_time":1.218005712},
{"learn":[4.444696901],"iteration":297,"passed_time":0.5158835894,"remaining_time":1.215269395},
{"learn":[4.442052813],"iteration":298,"passed_time":0.5169055817,"remaining_time":1.211875628},
{"learn":[4.440036756],"iteration":299,"passed_time":0.5178868832,"remaining_time":1.208402728},
{"learn":[4.435017051],"iteration":300,"passed_time":0.5189886266,"remaining_time":1.20522608},
{"learn":[4.429962125],"iteration":301,"passed_time":0.5209702408,"remaining_time":1.204096782},
{"learn":[4.427666256],"iteration":302,"passed_time":0.5219542955,"remaining_time":1.200667142},
{"learn":[4.425030004],"iteration":303,"passed_time":0.5232967714,"remaining_time":1.198074187},
{"learn":[4.422588771],"iteration":304,"passed_time":0.5248430173,"remaining_time":1.195953761},
{"learn":[4.418936667],"iteration":305,"passed_time":0.5260838041,"remaining_time":1.193144314},
{"learn":[4.416887976],"iteration":306,"passed_time":0.5273322579,"remaining_time":1.190362393},
{"learn":[4.413773354],"iteration":307,"passed_time":0.5285247014,"remaining_time":1.187464589},
{"learn":[4.411129391],"iteration":308,"passed_time":0.5297106571,"remaining_time":1.184563314},
{"learn":[4.40850819],"iteration":309,"passed_time":0.530940883,"remaining_time":1.181771643},
{"learn":[4.404880292],"iteration":310,"passed_time":0.5319804031,"remaining_time":1.178567517},
{"learn":[4.404593827],"iteration":311,"passed_time":0.5335197238,"remaining_time":1.176479391},
{"learn":[4.402139942],"iteration":312,"passed_time":0.5346302425,"remaining_time":1.173453599},
{"learn":[4.400284725],"iteration":313,"passed_time":0.5356436343,"remaining_time":1.170227812},
{"learn":[4.395805521],"iteration":314,"passed_time":0.5364872748,"remaining_time":1.166646931},
{"learn":[4.392838833],"iteration":315,"passed_time":0.5375172612,"remaining_time":1.16348673},
{"learn":[4.389213061],"iteration":316,"passed_time":0.5389233388,"remaining_time":1.161150285},
{"learn":[4.3861981],"iteration":317,"passed_time":0.5402997137,"remaining_time":1.15875599},
{"learn":[4.385054234],"iteration":318,"passed_time":0.5414848439,"remaining_time":1.155959808},
{"learn":[4.379364607],"iteration":319,"passed_time":0.542503673,"remaining_time":1.152820305},
{"learn":[4.378387619],"iteration":320,"passed_time":0.5434052998,"remaining_time":1.149446101},
{"learn":[4.375816727],"iteration":321,"passed_time":0.5444773702,"remaining_time":1.14644614},
{"learn":[4.374600202],"iteration":322,"passed_time":0.5454813588,"remaining_time":1.143315418},
{"learn":[4.37098897],"iteration":323,"passed_time":0.546459244,"remaining_time":1.140143361},
{"learn":[4.367418484],"iteration":324,"passed_time":0.5477053147,"remaining_time":1.137541807},
{"learn":[4.363584638],"iteration":325,"passed_time":0.5491372695,"remaining_time":1.135332882},
{"learn":[4.360770706],"iteration":326,"passed_time":0.5504516936,"remaining_time":1.132886819},
{"learn":[4.358675808],"iteration":327,"passed_time":0.5515380037,"remaining_time":1.1299803},
{"learn":[4.354228195],"iteration":328,"passed_time":0.5528049908,"remaining_time":1.12745334},
{"learn":[4.353773425],"iteration":329,"passed_time":0.5538095376,"remaining_time":1.124401182},
{"learn":[4.351648009],"iteration":330,"passed_time":0.554896977,"remaining_time":1.121528935},
{"learn":[4.348209927],"iteration":331,"passed_time":0.5559877588,"remaining_time":1.118674165},
{"learn":[4.345852733],"iteration":332,"passed_time":0.5569816443,"remaining_time":1.115635906},
{"learn":[4.34237339],"iteration":333,"passed_time":0.558083554,"remaining_time":1.11282529},
{"learn":[4.340814362],"iteration":334,"passed_time":0.5590993666,"remaining_time":1.109853967},
{"learn":[4.339707068],"iteration":335,"passed_time":0.5600969747,"remaining_time":1.106858307},
{"learn":[4.335430786],"iteration":336,"passed_time":0.5611262541,"remaining_time":1.103936815},
{"learn":[4.33521887],"iteration":337,"passed_time":0.5621647434,"remaining_time":1.101044557},
{"learn":[4.328507238],"iteration":338,"passed_time":0.5638076059,"remaining_time":1.099341674},
{"learn":[4.326140732],"iteration":339,"passed_time":0.5649941696,"remaining_time":1.096753388},
{"learn":[4.323785636],"iteration":340,"passed_time":0.5660335876,"remaining_time":1.093888957},
{"learn":[4.320632534],"iteration":341,"passed_time":0.5669644328,"remaining_time":1.090826306},
{"learn":[4.31973724],"iteration":342,"passed_time":0.5678834174,"remaining_time":1.087753368},
{"learn":[4.318000924],"iteration":343,"passed_time":0.5688755772,"remaining_time":1.084832496},
{"learn":[4.312713628],"iteration":344,"passed_time":0.5701722734,"remaining_time":1.082500983},
{"learn":[4.308220789],"iteration":345,"passed_time":0.5712888223,"remaining_time":1.079834942},
{"learn":[4.305890947],"iteration":346,"passed_time":0.5723893974,"remaining_time":1.077147771},
{"learn":[4.305137856],"iteration":347,"passed_time":0.573500664,"remaining_time":1.07448975},
{"learn":[4.304787172],"iteration":348,"passed_time":0.5743553067,"remaining_time":1.071361904},
{"learn":[4.30350134],"iteration":349,"passed_time":0.5753615988,"remaining_time":1.068528684},
{"learn":[4.30293809],"iteration":350,"passed_time":0.5763133661,"remaining_time":1.065605056},
{"learn":[4.299548459],"iteration":351,"passed_time":0.5774600227,"remaining_time":1.063051405},
{"learn":[4.294768408],"iteration":352,"passed_time":0.5787417739,"remaining_time":1.060753336},
{"learn":[4.294581479],"iteration":353,"passed_time":0.5799754965,"remaining_time":1.058373364},
{"learn":[4.292551604],"iteration":354,"passed_time":0.5819485001,"remaining_time":1.05734305},
{"learn":[4.288628894],"iteration":355,"passed_time":0.5832338658,"remaining_time":1.05506351},
{"learn":[4.287802767],"iteration":356,"passed_time":0.5843734788,"remaining_time":1.052527022},
{"learn":[4.284566905],"iteration":357,"passed_time":0.5858813969,"remaining_time":1.050658818},
{"learn":[4.27890232],"iteration":358,"passed_time":0.5871929103,"remaining_time":1.048441937},
{"learn":[4.276938023],"iteration":359,"passed_time":0.5886833179,"remaining_time":1.046548121},
{"learn":[4.273425094],"iteration":360,"passed_time":0.5899061381,"remaining_time":1.044182887},
{"learn":[4.269726505],"iteration":361,"passed_time":0.5912392551,"remaining_time":1.042018356},
{"learn":[4.265565857],"iteration":362,"passed_time":0.592311786,"remaining_time":1.039401123},
{"learn":[4.262117173],"iteration":363,"passed_time":0.5934124307,"remaining_time":1.0368415},
{"learn":[4.259185148],"iteration":364,"passed_time":0.5958795078,"remaining_time":1.036667089},
{"learn":[4.257668507],"iteration":365,"passed_time":0.5970547715,"remaining_time":1.034242418},
{"learn":[4.253432436],"iteration":366,"passed_time":0.5981783046,"remaining_time":1.031735332},
{"learn":[4.250216667],"iteration":367,"passed_time":0.5990917321,"remaining_time":1.028874931},
{"learn":[4.24514828],"iteration":368,"passed_time":0.6003522245,"remaining_time":1.026618574},
{"learn":[4.244015772],"iteration":369,"passed_time":0.6017321371,"remaining_time":1.024570936},
{"learn":[4.240329192],"iteration":370,"passed_time":0.6032916413,"remaining_time":1.022831381},
{"learn":[4.236718014],"iteration":371,"passed_time":0.6044804294,"remaining_time":1.020466961},
{"learn":[4.233495944],"iteration":372,"passed_time":0.6057198277,"remaining_time":1.018193919},
{"learn":[4.230357491],"iteration":373,"passed_time":0.6072306599,"remaining_time":1.01638073},
{"learn":[4.227381215],"iteration":374,"passed_time":0.6082399641,"remaining_time":1.013733274},
{"learn":[4.226169067],"iteration":375,"passed_time":0.6101025314,"remaining_time":1.012510584},
{"learn":[4.225963861],"iteration":376,"passed_time":0.6115574228,"remaining_time":1.010610807},
{"learn":[4.224346548],"iteration":377,"passed_time":0.6127524508,"remaining_time":1.008285779},
{"learn":[4.222595381],"iteration":378,"passed_time":0.6140961303,"remaining_time":1.006210282},
{"learn":[4.219700938],"iteration":379,"passed_time":0.61534611,"remaining_time":1.003985758},
{"learn":[4.216356207],"iteration":380,"passed_time":0.6165233004,"remaining_time":1.001648092},
{"learn":[4.214326494],"iteration":381,"passed_time":0.6178762889,"remaining_time":0.9996009072},
{"learn":[4.212901398],"iteration":382,"passed_time":0.6194134982,"remaining_time":0.9978541212},
{"learn":[4.211331091],"iteration":383,"passed_time":0.6207826257,"remaining_time":0.9958387955},
{"learn":[4.208624791],"iteration":384,"passed_time":0.6219127648,"remaining_time":0.9934450659},
{"learn":[4.204659106],"iteration":385,"passed_time":0.6230351313,"remaining_time":0.9910455197},
{"learn":[4.202968852],"iteration":386,"passed_time":0.624375824,"remaining_time":0.9889983983},
{"learn":[4.197261935],"iteration":387,"passed_time":0.6263047643,"remaining_time":0.9878827726},
{"learn":[4.196934403],"iteration":388,"passed_time":0.6277751123,"remaining_time":0.9860426572},
{"learn":[4.192479929],"iteration":389,"passed_time":0.6290348162,"remaining_time":0.983874969},
{"learn":[4.190243116],"iteration":390,"passed_time":0.6300372219,"remaining_time":0.9813111717},
{"learn":[4.185852431],"iteration":391,"passed_time":0.6310845605,"remaining_time":0.9788250325},
{"learn":[4.180967944],"iteration":392,"passed_time":0.6324542695,"remaining_time":0.9768441261},
{"learn":[4.178283162],"iteration":393,"passed_time":0.6338951202,"remaining_time":0.9749757432},
{"learn":[4.176341157],"iteration":394,"passed_time":0.6352658861,"remaining_time":0.97300218},
{"learn":[4.176041504],"iteration":395,"passed_time":0.6364678975,"remaining_time":0.9707742679},
{"learn":[4.175564513],"iteration":396,"passed_time":0.6376705463,"remaining_time":0.9685524922},
{"learn":[4.170830274],"iteration":397,"passed_time":0.6391786626,"remaining_time":0.9667978766},
{"learn":[4.167804808],"iteration":398,"passed_time":0.6412651403,"remaining_time":0.9659156624},
{"learn":[4.165860548],"iteration":399,"passed_time":0.6426620868,"remaining_time":0.9639931303},
{"learn":[4.160950571],"iteration":400,"passed_time":0.6437138481,"remaining_time":0.9615575935},
{"learn":[4.158544115],"iteration":401,"passed_time":0.6451357387,"remaining_time":0.9596795316},
{"learn":[4.154448767],"iteration":402,"passed_time":0.6462291825,"remaining_time":0.957317176},
{"learn":[4.15197457],"iteration":403,"passed_time":0.6475857296,"remaining_time":0.9553492447},
{"learn":[4.149562679],"iteration":404,"passed_time":0.6492066385,"remaining_time":0.9537727158},
{"learn":[4.149327961],"iteration":405,"passed_time":0.6504881727,"remaining_time":0.9516994447},
{"learn":[4.147444889],"iteration":406,"passed_time":0.6516409824,"remaining_time":0.9494425124},
{"learn":[4.147254809],"iteration":407,"passed_time":0.6525773924,"remaining_time":0.9468770007},
{"learn":[4.144589165],"iteration":408,"passed_time":0.6536133647,"remaining_time":0.9444633216},
{"learn":[4.141691034],"iteration":409,"passed_time":0.655670673,"remaining_time":0.9435260904},
{"learn":[4.138893468],"iteration":410,"passed_time":0.6574573673,"remaining_time":0.9421955945},
{"learn":[4.136964597],"iteration":411,"passed_time":0.6589200355,"remaining_time":0.940400439},
{"learn":[4.133773523],"iteration":412,"passed_time":0.6600129496,"remaining_time":0.9380813594},
{"learn":[4.131363444],"iteration":413,"passed_time":0.6610671844,"remaining_time":0.9357134542},
{"learn":[4.130228592],"iteration":414,"passed_time":0.6622174751,"remaining_time":0.9334872842},
{"learn":[4.12884186],"iteration":415,"passed_time":0.6637296813,"remaining_time":0.9317743603},
{"learn":[4.12413494],"iteration":416,"passed_time":0.6650985118,"remaining_time":0.9298619482},
{"learn":[4.119422508],"iteration":417,"passed_time":0.6664580763,"remaining_time":0.9279392354},
{"learn":[4.117038244],"iteration":418,"passed_time":0.6676871203,"remaining_time":0.9258382265},
{"learn":[4.116067631],"iteration":419,"passed_time":0.6686058035,"remaining_time":0.9233127763},
{"learn":[4.110343455],"iteration":420,"passed_time":0.6699671117,"remaining_time":0.9214037},
{"learn":[4.105604544],"iteration":421,"passed_time":0.6718255714,"remaining_time":0.9201781523},
{"learn":[4.103390131],"iteration":422,"passed_time":0.6734064265,"remaining_time":0.9185709411},
{"learn":[4.096724402],"iteration":423,"passed_time":0.6744089506,"remaining_time":0.9161781971},
{"learn":[4.093431279],"iteration":424,"passed_time":0.6755175287,"remaining_time":0.91393548},
{"learn":[4.091412744],"iteration":425,"passed_time":0.6770217689,"remaining_time":0.9122312097},
{"learn":[4.091192901],"iteration":426,"passed_time":0.6780637686,"remaining_time":0.9099075864},
{"learn":[4.088994581],"iteration":427,"passed_time":0.6797461286,"remaining_time":0.9084457607},
{"learn":[4.087845355],"iteration":428,"passed_time":0.6809954493,"remaining_time":0.9064065304},
{"learn":[4.083650279],"iteration":429,"passed_time":0.6820378721,"remaining_time":0.9040967142},
{"learn":[4.079840652],"iteration":430,"passed_time":0.683117624,"remaining_time":0.9018420605},
{"learn":[4.075707828],"iteration":431,"passed_time":0.6841784817,"remaining_time":0.8995680037},
{"learn":[4.071345409],"iteration":432,"passed_time":0.6861749942,"remaining_time":0.8985247615},
{"learn":[4.067460475],"iteration":433,"passed_time":0.6876253015,"remaining_time":0.8967647941},
{"learn":[4.064914749],"iteration":434,"passed_time":0.6889545263,"remaining_time":0.8948489824},
{"learn":[4.063823175],"iteration":435,"passed_time":0.6900364186,"remaining_time":0.8926159176},
{"learn":[4.058898471],"iteration":436,"passed_time":0.6910861198,"remaining_time":0.8903466486},
{"learn":[4.054120355],"iteration":437,"passed_time":0.692328496,"remaining_time":0.8883301707},
{"learn":[4.052715901],"iteration":438,"passed_time":0.6936666369,"remaining_time":0.8864395975},
{"learn":[4.052114167],"iteration":439,"passed_time":0.695034703,"remaining_time":0.884589622},
{"learn":[4.051377267],"iteration":440,"passed_time":0.6964366891,"remaining_time":0.8827848281},
{"learn":[4.049275336],"iteration":441,"passed_time":0.6974576871,"remaining_time":0.880500881},
{"learn":[4.047099198],"iteration":442,"passed_time":0.6986604054,"remaining_time":0.8784511192},
{"learn":[4.044348685],"iteration":443,"passed_time":0.7000398563,"remaining_time":0.8766264867},
{"learn":[4.042822379],"iteration":444,"passed_time":0.7015569119,"remaining_time":0.8749754744},
{"learn":[4.041258611],"iteration":445,"passed_time":0.7031886405,"remaining_time":0.8734675041},
{"learn":[4.040044254],"iteration":446,"passed_time":0.7043552852,"remaining_time":0.8713836078},
{"learn":[4.036860137],"iteration":447,"passed_time":0.7055672285,"remaining_time":0.8693596209},
{"learn":[4.036372284],"iteration":448,"passed_time":0.7065829572,"remaining_time":0.8670984619},
{"learn":[4.03368231],"iteration":449,"passed_time":0.7078961419,"remaining_time":0.8652063957},
{"learn":[4.032439519],"iteration":450,"passed_time":0.7092302849,"remaining_time":0.8633424089},
{"learn":[4.032008634],"iteration":451,"passed_time":0.710414959,"remaining_time":0.861299552},
{"learn":[4.030034932],"iteration":452,"passed_time":0.7114934759,"remaining_time":0.8591322987},
{"learn":[4.028173412],"iteration":453,"passed_time":0.7126966624,"remaining_time":0.8571197746},
{"learn":[4.023806097],"iteration":454,"passed_time":0.7140647454,"remaining_time":0.8553083214},
{"learn":[4.020239186],"iteration":455,"passed_time":0.7154631664,"remaining_time":0.8535350056},
{"learn":[4.017384838],"iteration":456,"passed_time":0.7168517849,"remaining_time":0.8517516832},
{"learn":[4.016468229],"iteration":457,"passed_time":0.7182267842,"remaining_time":0.8499539674},
{"learn":[4.014530169],"iteration":458,"passed_time":0.7196158327,"remaining_time":0.8481746525},
{"learn":[4.012884822],"iteration":459,"passed_time":0.7207219328,"remaining_time":0.8460648776},
{"learn":[4.008924707],"iteration":460,"passed_time":0.7218027248,"remaining_time":0.8439298669},
{"learn":[4.008286778],"iteration":461,"passed_time":0.7229450737,"remaining_time":0.8418711031},
{"learn":[4.006444202],"iteration":462,"passed_time":0.7243871119,"remaining_time":0.8401638857},
{"learn":[4.003284363],"iteration":463,"passed_time":0.7257224022,"remaining_time":0.8383344991},
{"learn":[3.999811484],"iteration":464,"passed_time":0.7269500509,"remaining_time":0.8363833919},
{"learn":[3.997483319],"iteration":465,"passed_time":0.7281393156,"remaining_time":0.8343914046},
{"learn":[3.99708333],"iteration":466,"passed_time":0.7291943827,"remaining_time":0.8322496916},
{"learn":[3.995860263],"iteration":467,"passed_time":0.7301832238,"remaining_time":0.8300373399},
{"learn":[3.994131111],"iteration":468,"passed_time":0.7315719082,"remaining_time":0.8282829067},
{"learn":[3.993125499],"iteration":469,"passed_time":0.7332308441,"remaining_time":0.8268347817},
{"learn":[3.992954084],"iteration":470,"passed_time":0.7344251146,"remaining_time":0.824863876},
{"learn":[3.990635743],"iteration":471,"passed_time":0.7355026284,"remaining_time":0.8227656521},
{"learn":[3.986678254],"iteration":472,"passed_time":0.7365376776,"remaining_time":0.8206244315},
{"learn":[3.986393291],"iteration":473,"passed_time":0.7376109649,"remaining_time":0.8185303113},
{"learn":[3.986152671],"iteration":474,"passed_time":0.7389155608,"remaining_time":0.8166961462},
{"learn":[3.985596662],"iteration":475,"passed_time":0.7401808251,"remaining_time":0.8148209083},
{"learn":[3.983853457],"iteration":476,"passed_time":0.7413799389,"remaining_time":0.8128756983},
{"learn":[3.983263928],"iteration":477,"passed_time":0.7423902447,"remaining_time":0.810727422},
{"learn":[3.980067202],"iteration":478,"passed_time":0.7434466656,"remaining_time":0.8086340559},
{"learn":[3.978115407],"iteration":479,"passed_time":0.7445056024,"remaining_time":0.8065477359},
{"learn":[3.972661644],"iteration":480,"passed_time":0.7456182462,"remaining_time":0.8045236378},
{"learn":[3.969938254],"iteration":481,"passed_time":0.7483801359,"remaining_time":0.8042757477},
{"learn":[3.968211434],"iteration":482,"passed_time":0.749966192,"remaining_time":0.8027588432},
{"learn":[3.966113368],"iteration":483,"passed_time":0.7515138417,"remaining_time":0.8012007072},
{"learn":[3.962246044],"iteration":484,"passed_time":0.7526345198,"remaining_time":0.7991892324},
{"learn":[3.961319703],"iteration":485,"passed_time":0.7545465902,"remaining_time":0.7980184102},
{"learn":[3.96078191],"iteration":486,"passed_time":0.7560012152,"remaining_time":0.7963626764},
{"learn":[3.958913633],"iteration":487,"passed_time":0.7574660346,"remaining_time":0.7947184625},
{"learn":[3.957428286],"iteration":488,"passed_time":0.7585172738,"remaining_time":0.7926427953},
{"learn":[3.952641965],"iteration":489,"passed_time":0.7595494407,"remaining_time":0.7905514587},
{"learn":[3.951486786],"iteration":490,"passed_time":0.760573749,"remaining_time":0.7884562897},
{"learn":[3.94938344],"iteration":491,"passed_time":0.7628483356,"remaining_time":0.7876564115},
{"learn":[3.947297924],"iteration":492,"passed_time":0.7642040883,"remaining_time":0.7859056242},
{"learn":[3.946284886],"iteration":493,"passed_time":0.7651163877,"remaining_time":0.7837022109},
{"learn":[3.943288204],"iteration":494,"passed_time":0.7663024571,"remaining_time":0.7817833148},
{"learn":[3.943076488],"iteration":495,"passed_time":0.7672430313,"remaining_time":0.7796179189},
{"learn":[3.942347078],"iteration":496,"passed_time":0.7683103684,"remaining_time":0.7775857451},
{"learn":[3.940251541],"iteration":497,"passed_time":0.7697319154,"remaining_time":0.7759145011},
{"learn":[3.939011019],"iteration":498,"passed_time":0.7709583761,"remaining_time":0.7740483897},
{"learn":[3.938760512],"iteration":499,"passed_time":0.7720270206,"remaining_time":0.7720270206},
{"learn":[3.934522727],"iteration":500,"passed_time":0.7733852878,"remaining_time":0.7702979213},
{"learn":[3.930091193],"iteration":501,"passed_time":0.7744938313,"remaining_time":0.7683225657},
{"learn":[3.927671752],"iteration":502,"passed_time":0.7754384085,"remaining_time":0.7661886462},
{"learn":[3.927280041],"iteration":503,"passed_time":0.7766500782,"remaining_time":0.7643222992},
{"learn":[3.925987561],"iteration":504,"passed_time":0.7786473499,"remaining_time":0.7632285905},
{"learn":[3.921645957],"iteration":505,"passed_time":0.7798425447,"remaining_time":0.7613482551},
{"learn":[3.920333743],"iteration":506,"passed_time":0.781072867,"remaining_time":0.75950478},
{"learn":[3.918659461],"iteration":507,"passed_time":0.7821643461,"remaining_time":0.7575292486},
{"learn":[3.916124385],"iteration":508,"passed_time":0.7832734297,"remaining_time":0.7555741728},
{"learn":[3.913849268],"iteration":509,"passed_time":0.7843771559,"remaining_time":0.7536172674},
{"learn":[3.912826119],"iteration":510,"passed_time":0.785634684,"remaining_time":0.7518108816},
{"learn":[3.910034145],"iteration":511,"passed_time":0.786853749,"remaining_time":0.7499699796},
{"learn":[3.90792379],"iteration":512,"passed_time":0.788101256,"remaining_time":0.7481585023},
{"learn":[3.907823851],"iteration":513,"passed_time":0.7891351008,"remaining_time":0.7461471965},
{"learn":[3.904527401],"iteration":514,"passed_time":0.7902045036,"remaining_time":0.7441731733},
{"learn":[3.903378283],"iteration":515,"passed_time":0.7912530699,"remaining_time":0.7421831121},
{"learn":[3.902170135],"iteration":516,"passed_time":0.793004629,"remaining_time":0.7408534542},
{"learn":[3.899435429],"iteration":517,"passed_time":0.7944443018,"remaining_time":0.7392319565},
{"learn":[3.897497505],"iteration":518,"passed_time":0.7960204637,"remaining_time":0.7377376552},
{"learn":[3.896426119],"iteration":519,"passed_time":0.7972070676,"remaining_time":0.735883447},
{"learn":[3.896044669],"iteration":520,"passed_time":0.7983432513,"remaining_time":0.733985446},
{"learn":[3.892795942],"iteration":521,"passed_time":0.8002034463,"remaining_time":0.7327533474},
{"learn":[3.892413888],"iteration":522,"passed_time":0.8024290402,"remaining_time":0.7318521074},
{"learn":[3.891738985],"iteration":523,"passed_time":0.8048102389,"remaining_time":0.7310871636},
{"learn":[3.88822057],"iteration":524,"passed_time":0.8066618566,"remaining_time":0.7298369179},
{"learn":[3.883837053],"iteration":525,"passed_time":0.808346126,"remaining_time":0.7284335813},
{"learn":[3.881769742],"iteration":526,"passed_time":0.8099964465,"remaining_time":0.7269987082},
{"learn":[3.880356898],"iteration":527,"passed_time":0.8112046147,"remaining_time":0.7251677616},
{"learn":[3.879250273],"iteration":528,"passed_time":0.8124065168,"remaining_time":0.7233335905},
{"learn":[3.877174493],"iteration":529,"passed_time":0.8135374202,"remaining_time":0.7214388444},
{"learn":[3.875854201],"iteration":530,"passed_time":0.8151635273,"remaining_time":0.7199843584},
{"learn":[3.873189396],"iteration":531,"passed_time":0.8165586373,"remaining_time":0.7183260193},
{"learn":[3.871583368],"iteration":532,"passed_time":0.8178110126,"remaining_time":0.7165436077},
{"learn":[3.869622679],"iteration":533,"passed_time":0.8193635993,"remaining_time":0.7150251634},
{"learn":[3.866860164],"iteration":534,"passed_time":0.8212975425,"remaining_time":0.713838051},
{"learn":[3.864498444],"iteration":535,"passed_time":0.8239567622,"remaining_time":0.7132760031},
{"learn":[3.861416322],"iteration":536,"passed_time":0.8259261176,"remaining_time":0.7121113453},
{"learn":[3.860265769],"iteration":537,"passed_time":0.8268470067,"remaining_time":0.7100433403},
{"learn":[3.859328725],"iteration":538,"passed_time":0.8279233129,"remaining_time":0.7081125181},
{"learn":[3.858521278],"iteration":539,"passed_time":0.8290439581,"remaining_time":0.7062226309},
{"learn":[3.85599111],"iteration":540,"passed_time":0.8308074621,"remaining_time":0.7048810076},
{"learn":[3.852379816],"iteration":541,"passed_time":0.8320230473,"remaining_time":0.7030748259},
{"learn":[3.851327537],"iteration":542,"passed_time":0.8333879306,"remaining_time":0.701396472},
{"learn":[3.847854898],"iteration":543,"passed_time":0.8344900975,"remaining_time":0.6994990523},
{"learn":[3.847083414],"iteration":544,"passed_time":0.8354327277,"remaining_time":0.6974713598},
{"learn":[3.845397429],"iteration":545,"passed_time":0.8368087361,"remaining_time":0.6958079967},
{"learn":[3.841933528],"iteration":546,"passed_time":0.8382726119,"remaining_time":0.6942184519},
{"learn":[3.840996474],"iteration":547,"passed_time":0.8397110811,"remaining_time":0.6926084099},
{"learn":[3.838355966],"iteration":548,"passed_time":0.8411301517,"remaining_time":0.6909830572},
{"learn":[3.83342799],"iteration":549,"passed_time":0.8421571244,"remaining_time":0.6890376473},
{"learn":[3.828161535],"iteration":550,"passed_time":0.8434054127,"remaining_time":0.687275917},
{"learn":[3.823502399],"iteration":551,"passed_time":0.8446813954,"remaining_time":0.6855385238},
{"learn":[3.820068862],"iteration":552,"passed_time":0.8462509629,"remaining_time":0.6840401093},
{"learn":[3.817951642],"iteration":553,"passed_time":0.8474908137,"remaining_time":0.6822759981},
{"learn":[3.815785958],"iteration":554,"passed_time":0.8487572069,"remaining_time":0.6805350578},
{"learn":[3.81503012],"iteration":555,"passed_time":0.8497894301,"remaining_time":0.6786088255},
{"learn":[3.813529315],"iteration":556,"passed_time":0.8508664709,"remaining_time":0.6767214482},
{"learn":[3.808881326],"iteration":557,"passed_time":0.8524075141,"remaining_time":0.6752045184},
{"learn":[3.808740434],"iteration":558,"passed_time":0.8538063242,"remaining_time":0.6735752933},
{"learn":[3.80714352],"iteration":559,"passed_time":0.8551598059,"remaining_time":0.671911276},
{"learn":[3.80573346],"iteration":560,"passed_time":0.8565007996,"remaining_time":0.6702385936},
{"learn":[3.803370052],"iteration":561,"passed_time":0.8576272395,"remaining_time":0.668399877},
{"learn":[3.803215211],"iteration":562,"passed_time":0.8588459576,"remaining_time":0.666635317},
{"learn":[3.801309667],"iteration":563,"passed_time":0.8599928646,"remaining_time":0.664817179},
{"learn":[3.800003847],"iteration":564,"passed_time":0.8612332636,"remaining_time":0.6630733976},
{"learn":[3.798026138],"iteration":565,"passed_time":0.862467419,"remaining_time":0.6613266075},
{"learn":[3.794745847],"iteration":566,"passed_time":0.8636139008,"remaining_time":0.6595146721},
{"learn":[3.794312041],"iteration":567,"passed_time":0.8645864491,"remaining_time":0.6575727923},
{"learn":[3.792205926],"iteration":568,"passed_time":0.8658003564,"remaining_time":0.6558171417},
{"learn":[3.788991061],"iteration":569,"passed_time":0.8669196429,"remaining_time":0.6539920113},
{"learn":[3.787391572],"iteration":570,"passed_time":0.8686313447,"remaining_time":0.6526144429},
{"learn":[3.7826445],"iteration":571,"passed_time":0.8699385082,"remaining_time":0.6509330096},
{"learn":[3.781700331],"iteration":572,"passed_time":0.871305234,"remaining_time":0.6492972686},
{"learn":[3.780045374],"iteration":573,"passed_time":0.8726424727,"remaining_time":0.6476405808},
{"learn":[3.775462644],"iteration":574,"passed_time":0.8737497571,"remaining_time":0.6458150378},
{"learn":[3.773711943],"iteration":575,"passed_time":0.8752832474,"remaining_time":0.6443057238},
{"learn":[3.772415806],"iteration":576,"passed_time":0.8765422163,"remaining_time":0.6425950737},
{"learn":[3.770170875],"iteration":577,"passed_time":0.8776394032,"remaining_time":0.6407678688},
{"learn":[3.765166479],"iteration":578,"passed_time":0.8789259299,"remaining_time":0.6390808575},
{"learn":[3.763976102],"iteration":579,"passed_time":0.8803128758,"remaining_time":0.6374679445},
{"learn":[3.760761708],"iteration":580,"passed_time":0.8816544201,"remaining_time":0.6358230672},
{"learn":[3.758155662],"iteration":581,"passed_time":0.8838442671,"remaining_time":0.6347884943},
{"learn":[3.756844548],"iteration":582,"passed_time":0.8854806072,"remaining_time":0.6333540535},
{"learn":[3.753098923],"iteration":583,"passed_time":0.8870164726,"remaining_time":0.6318473504},
{"learn":[3.751618946],"iteration":584,"passed_time":0.888148986,"remaining_time":0.6300544089},
{"learn":[3.751398464],"iteration":585,"passed_time":0.889059483,"remaining_time":0.6281068702},
{"learn":[3.749920103],"iteration":586,"passed_time":0.8902582227,"remaining_time":0.6263656661},
{"learn":[3.748237465],"iteration":587,"passed_time":0.8922384746,"remaining_time":0.6251738971},
{"learn":[3.746021536],"iteration":588,"passed_time":0.8934062602,"remaining_time":0.6234125177},
{"learn":[3.74417648],"iteration":589,"passed_time":0.8944165193,"remaining_time":0.6215436829},
{"learn":[3.738788389],"iteration":590,"passed_time":0.8954192058,"remaining_time":0.619672513},
{"learn":[3.736021611],"iteration":591,"passed_time":0.8966723552,"remaining_time":0.6179768934},
{"learn":[3.734546151],"iteration":592,"passed_time":0.898616416,"remaining_time":0.6167569668},
{"learn":[3.733527479],"iteration":593,"passed_time":0.9007889543,"remaining_time":0.6156907667},
{"learn":[3.733026392],"iteration":594,"passed_time":0.9020469036,"remaining_time":0.6139983125},
{"learn":[3.730314752],"iteration":595,"passed_time":0.9036710809,"remaining_time":0.6125555649},
{"learn":[3.727342596],"iteration":596,"passed_time":0.9052775724,"remaining_time":0.6111002708},
{"learn":[3.725459604],"iteration":597,"passed_time":0.9068152515,"remaining_time":0.6095982125},
{"learn":[3.723158842],"iteration":598,"passed_time":0.9077585596,"remaining_time":0.6076981343},
{"learn":[3.722362756],"iteration":599,"passed_time":0.9087707144,"remaining_time":0.6058471429},
{"learn":[3.721443615],"iteration":600,"passed_time":0.9098382838,"remaining_time":0.6040357325},
{"learn":[3.720743486],"iteration":601,"passed_time":0.9111400722,"remaining_time":0.6023816424},
{"learn":[3.720215334],"iteration":602,"passed_time":0.9126476427,"remaining_time":0.6008642026},
{"learn":[3.719436563],"iteration":603,"passed_time":0.9139335526,"remaining_time":0.5992014682},
{"learn":[3.715046574],"iteration":604,"passed_time":0.9153086013,"remaining_time":0.5975981777},
{"learn":[3.71443396],"iteration":605,"passed_time":0.9168173204,"remaining_time":0.5960825483},
{"learn":[3.712938941],"iteration":606,"passed_time":0.918088999,"remaining_time":0.5944134705},
{"learn":[3.712814764],"iteration":607,"passed_time":0.9193087239,"remaining_time":0.5927122036},
{"learn":[3.71235348],"iteration":608,"passed_time":0.9203522969,"remaining_time":0.5908994222},
{"learn":[3.711223749],"iteration":609,"passed_time":0.9212552612,"remaining_time":0.5889992653},
{"learn":[3.710755648],"iteration":610,"passed_time":0.9223184409,"remaining_time":0.5872043756},
{"learn":[3.708668039],"iteration":611,"passed_time":0.9235090089,"remaining_time":0.5854926396},
{"learn":[3.705623591],"iteration":612,"passed_time":0.9247524947,"remaining_time":0.5838160121},
{"learn":[3.704045802],"iteration":613,"passed_time":0.9258789823,"remaining_time":0.582067243},
{"learn":[3.699915209],"iteration":614,"passed_time":0.9269188524,"remaining_time":0.5802662735},
{"learn":[3.696182221],"iteration":615,"passed_time":0.928750022,"remaining_time":0.5789610526},
{"learn":[3.694263278],"iteration":616,"passed_time":0.9305734582,"remaining_time":0.5776493265},
{"learn":[3.693810229],"iteration":617,"passed_time":0.9317513216,"remaining_time":0.5759369011},
{"learn":[3.690900932],"iteration":618,"passed_time":0.9328791877,"remaining_time":0.574195429},
{"learn":[3.688020895],"iteration":619,"passed_time":0.9348167901,"remaining_time":0.5729522262},
{"learn":[3.685491894],"iteration":620,"passed_time":0.936206353,"remaining_time":0.5713723153},
{"learn":[3.684328128],"iteration":621,"passed_time":0.9376635423,"remaining_time":0.5698341142},
{"learn":[3.680640153],"iteration":622,"passed_time":0.9389093285,"remaining_time":0.5681682453},
{"learn":[3.678932783],"iteration":623,"passed_time":0.9404578582,"remaining_time":0.5666861453},
{"learn":[3.674167041],"iteration":624,"passed_time":0.941959479,"remaining_time":0.5651756874},
{"learn":[3.672200976],"iteration":625,"passed_time":0.9441555547,"remaining_time":0.5640801557},
{"learn":[3.670606604],"iteration":626,"passed_time":0.9456552597,"remaining_time":0.5625668451},
{"learn":[3.665506042],"iteration":627,"passed_time":0.9471406821,"remaining_time":0.5610451174},
{"learn":[3.664214007],"iteration":628,"passed_time":0.9485901575,"remaining_time":0.5595023027},
{"learn":[3.66261643],"iteration":629,"passed_time":0.9501475397,"remaining_time":0.5580231583},
{"learn":[3.662118449],"iteration":630,"passed_time":0.9514187911,"remaining_time":0.5563764405},
{"learn":[3.660871366],"iteration":631,"passed_time":0.9529411278,"remaining_time":0.5548771124},
{"learn":[3.656695243],"iteration":632,"passed_time":0.9545770877,"remaining_time":0.553443588},
{"learn":[3.654497801],"iteration":633,"passed_time":0.9565452298,"remaining_time":0.5522011894},
{"learn":[3.654189134],"iteration":634,"passed_time":0.9585887679,"remaining_time":0.5509998429},
{"learn":[3.653957699],"iteration":635,"passed_time":0.9599730967,"remaining_time":0.5494185648},
{"learn":[3.651920725],"iteration":636,"passed_time":0.9613456361,"remaining_time":0.5478311867},
{"learn":[3.65106705],"iteration":637,"passed_time":0.9631335373,"remaining_time":0.5464801575},
{"learn":[3.650612844],"iteration":638,"passed_time":0.9656779418,"remaining_time":0.5455551439},
{"learn":[3.649884732],"iteration":639,"passed_time":0.9671229515,"remaining_time":0.5440066602},
{"learn":[3.646276182],"iteration":640,"passed_time":0.9685364662,"remaining_time":0.5424408602},
{"learn":[3.645808194],"iteration":641,"passed_time":0.9698977306,"remaining_time":0.5408463981},
{"learn":[3.645042989],"iteration":642,"passed_time":0.9712570097,"remaining_time":0.539251559},
{"learn":[3.639864499],"iteration":643,"passed_time":0.9728463504,"remaining_time":0.5377846285},
{"learn":[3.637318478],"iteration":644,"passed_time":0.9752800147,"remaining_time":0.5367820236},
{"learn":[3.636344905],"iteration":645,"passed_time":0.9766596159,"remaining_time":0.5351973747},
{"learn":[3.634754643],"iteration":646,"passed_time":0.9780323655,"remaining_time":0.5336096214},
{"learn":[3.630724975],"iteration":647,"passed_time":0.9798967609,"remaining_time":0.5322895985},
{"learn":[3.629408252],"iteration":648,"passed_time":0.9811968952,"remaining_time":0.5306627276},
{"learn":[3.62790646],"iteration":649,"passed_time":0.9824117582,"remaining_time":0.5289909467},
{"learn":[3.627388973],"iteration":650,"passed_time":0.9838103725,"remaining_time":0.5274190783},
{"learn":[3.625163557],"iteration":651,"passed_time":0.9850148587,"remaining_time":0.525744127},
{"learn":[3.623701985],"iteration":652,"passed_time":0.9861280944,"remaining_time":0.5240221268},
{"learn":[3.622342639],"iteration":653,"passed_time":0.9877921246,"remaining_time":0.522593387},
{"learn":[3.621130639],"iteration":654,"passed_time":0.9897792541,"remaining_time":0.5213341109},
{"learn":[3.619125665],"iteration":655,"passed_time":0.9924085854,"remaining_time":0.5204093802},
{"learn":[3.618878783],"iteration":656,"passed_time":0.9939382833,"remaining_time":0.5189053747},
{"learn":[3.616207429],"iteration":657,"passed_time":0.9953074988,"remaining_time":0.5173178793},
{"learn":[3.61206486],"iteration":658,"passed_time":0.9966565076,"remaining_time":0.5157205904},
{"learn":[3.611955873],"iteration":659,"passed_time":0.9977111908,"remaining_time":0.5139724316},
{"learn":[3.610713743],"iteration":660,"passed_time":0.9986981226,"remaining_time":0.5121916242},
{"learn":[3.610044025],"iteration":661,"passed_time":0.9999150907,"remaining_time":0.5105306656},
{"learn":[3.607342669],"iteration":662,"passed_time":1.001084456,"remaining_time":0.50884685},
{"learn":[3.602510618],"iteration":663,"passed_time":1.002738606,"remaining_time":0.5074098972},
{"learn":[3.600492392],"iteration":664,"passed_time":1.005442018,"remaining_time":0.5065008662},
{"learn":[3.597171065],"iteration":665,"passed_time":1.006703697,"remaining_time":0.5048634155},
{"learn":[3.594358798],"iteration":666,"passed_time":1.007972872,"remaining_time":0.5032308342},
{"learn":[3.593945251],"iteration":667,"passed_time":1.008898696,"remaining_time":0.5014286931},
{"learn":[3.593607748],"iteration":668,"passed_time":1.010113269,"remaining_time":0.4997720361},
{"learn":[3.592238714],"iteration":669,"passed_time":1.011332148,"remaining_time":0.4981188193},
{"learn":[3.590144654],"iteration":670,"passed_time":1.01261782,"remaining_time":0.4964996466},
{"learn":[3.587151536],"iteration":671,"passed_time":1.014587479,"remaining_time":0.4952153174},
{"learn":[3.586070865],"iteration":672,"passed_time":1.016478329,"remaining_time":0.4938906592},
{"learn":[3.585102746],"iteration":673,"passed_time":1.018628274,"remaining_time":0.4926896401},
{"learn":[3.584362847],"iteration":674,"passed_time":1.020566141,"remaining_time":0.4913836976},
{"learn":[3.581407561],"iteration":675,"passed_time":1.022027514,"remaining_time":0.4898475067},
{"learn":[3.57919422],"iteration":676,"passed_time":1.023755585,"remaining_time":0.4884387797},
{"learn":[3.577632204],"iteration":677,"passed_time":1.025220179,"remaining_time":0.4869039788},
{"learn":[3.573911195],"iteration":678,"passed_time":1.026855126,"remaining_time":0.4854499195},
{"learn":[3.573408216],"iteration":679,"passed_time":1.028232979,"remaining_time":0.4838743431},
{"learn":[3.571076482],"iteration":680,"passed_time":1.029655203,"remaining_time":0.4823201316},
{"learn":[3.568177107],"iteration":681,"passed_time":1.03149278,"remaining_time":0.4809599764},
{"learn":[3.564824621],"iteration":682,"passed_time":1.034070473,"remaining_time":0.4799419328},
{"learn":[3.562475026],"iteration":683,"passed_time":1.035836271,"remaining_time":0.4785442423},
{"learn":[3.561226889],"iteration":684,"passed_time":1.037898287,"remaining_time":0.477281694},
{"learn":[3.559383467],"iteration":685,"passed_time":1.039952037,"remaining_time":0.4760130317},
{"learn":[3.555209766],"iteration":686,"passed_time":1.042224595,"remaining_time":0.4748417734},
{"learn":[3.55345383],"iteration":687,"passed_time":1.044003333,"remaining_time":0.4734433721},
{"learn":[3.552300968],"iteration":688,"passed_time":1.04598374,"remaining_time":0.4721348958},
{"learn":[3.551253986],"iteration":689,"passed_time":1.04853636,"remaining_time":0.4710815528},
{"learn":[3.549807725],"iteration":690,"passed_time":1.051094924,"remaining_time":0.4700265288},
{"learn":[3.547992926],"iteration":691,"passed_time":1.052517895,"remaining_time":0.4684617219},
{"learn":[3.545438607],"iteration":692,"passed_time":1.053756126,"remaining_time":0.4668154843},
{"learn":[3.543313763],"iteration":693,"passed_time":1.05504954,"remaining_time":0.4651947539},
{"learn":[3.542962896],"iteration":694,"passed_time":1.056323113,"remaining_time":0.4635662584},
{"learn":[3.539800465],"iteration":695,"passed_time":1.057603846,"remaining_time":0.4619419097},
{"learn":[3.53953187],"iteration":696,"passed_time":1.058736818,"remaining_time":0.4602543126},
{"learn":[3.536332425],"iteration":697,"passed_time":1.060032182,"remaining_time":0.4586385659},
{"learn":[3.534993327],"iteration":698,"passed_time":1.061151307,"remaining_time":0.4569478446},
{"learn":[3.531637011],"iteration":699,"passed_time":1.06270652,"remaining_time":0.4554456516},
{"learn":[3.531040284],"iteration":700,"passed_time":1.064042971,"remaining_time":0.4538499976},
{"learn":[3.529973872],"iteration":701,"passed_time":1.065467716,"remaining_time":0.452292563},
{"learn":[3.527325183],"iteration":702,"passed_time":1.06688144,"remaining_time":0.4507308504},
{"learn":[3.527200815],"iteration":703,"passed_time":1.068154101,"remaining_time":0.4491102471},
{"learn":[3.523459911],"iteration":704,"passed_time":1.069472807,"remaining_time":0.4475098978},
{"learn":[3.522729934],"iteration":705,"passed_time":1.070701734,"remaining_time":0.4458729602},
{"learn":[3.522260582],"iteration":706,"passed_time":1.072224066,"remaining_time":0.4443587713},
{"learn":[3.518641591],"iteration":707,"passed_time":1.073576944,"remaining_time":0.4427746718},
{"learn":[3.516856405],"iteration":708,"passed_time":1.074865597,"remaining_time":0.4411648644},
{"learn":[3.515083413],"iteration":709,"passed_time":1.075916577,"remaining_time":0.4394588836},
{"learn":[3.514671214],"iteration":710,"passed_time":1.07763393,"remaining_time":0.438025606},
{"learn":[3.512617621],"iteration":711,"passed_time":1.080104454,"remaining_time":0.4368961835},
{"learn":[3.510747971],"iteration":712,"passed_time":1.082584901,"remaining_time":0.4357669937},
{"learn":[3.508149266],"iteration":713,"passed_time":1.084568662,"remaining_time":0.4344350664},
{"learn":[3.504557165],"iteration":714,"passed_time":1.085897372,"remaining_time":0.4328402111},
{"learn":[3.501367208],"iteration":715,"passed_time":1.087369245,"remaining_time":0.431302885},
{"learn":[3.497593362],"iteration":716,"passed_time":1.088627179,"remaining_time":0.4296812994},
{"learn":[3.496291169],"iteration":717,"passed_time":1.089887859,"remaining_time":0.4280618052},
{"learn":[3.49330374],"iteration":718,"passed_time":1.090917526,"remaining_time":0.4263530249},
{"learn":[3.490044385],"iteration":719,"passed_time":1.09216977,"remaining_time":0.4247326884},
{"learn":[3.488891789],"iteration":720,"passed_time":1.094465704,"remaining_time":0.4235172419},
{"learn":[3.486869081],"iteration":721,"passed_time":1.095686117,"remaining_time":0.421884682},
{"learn":[3.486303638],"iteration":722,"passed_time":1.096887924,"remaining_time":0.4202461342},
{"learn":[3.486035862],"iteration":723,"passed_time":1.097965013,"remaining_time":0.4185612481},
{"learn":[3.482668951],"iteration":724,"passed_time":1.098966917,"remaining_time":0.4168495202},
{"learn":[3.47820549],"iteration":725,"passed_time":1.100105814,"remaining_time":0.4151914504},
{"learn":[3.474392283],"iteration":726,"passed_time":1.101197594,"remaining_time":0.4135171157},
{"learn":[3.472268163],"iteration":727,"passed_time":1.102245204,"remaining_time":0.4118278786},
{"learn":[3.471209164],"iteration":728,"passed_time":1.103289421,"remaining_time":0.41013914},
{"learn":[3.470049971],"iteration":729,"passed_time":1.104223885,"remaining_time":0.4084115737},
{"learn":[3.469078654],"iteration":730,"passed_time":1.105400009,"remaining_time":0.4067751059},
{"learn":[3.468643292],"iteration":731,"passed_time":1.106434454,"remaining_time":0.4050880242},
{"learn":[3.468134848],"iteration":732,"passed_time":1.107644085,"remaining_time":0.4034665358},
{"learn":[3.467820182],"iteration":733,"passed_time":1.109853472,"remaining_time":0.4022084791},
{"learn":[3.465776156],"iteration":734,"passed_time":1.111874825,"remaining_time":0.400880039},
{"learn":[3.463037608],"iteration":735,"passed_time":1.11311482,"remaining_time":0.3992694464},
{"learn":[3.45965637],"iteration":736,"passed_time":1.114244072,"remaining_time":0.3976203404},
{"learn":[3.457275091],"iteration":737,"passed_time":1.115376049,"remaining_time":0.3959736107},
{"learn":[3.455522955],"iteration":738,"passed_time":1.116507139,"remaining_time":0.3943279612},
{"learn":[3.451270508],"iteration":739,"passed_time":1.117597057,"remaining_time":0.3926692361},
{"learn":[3.450978947],"iteration":740,"passed_time":1.118654868,"remaining_time":0.3910008245},
{"learn":[3.450608492],"iteration":741,"passed_time":1.119682384,"remaining_time":0.3893235244},
{"learn":[3.448122004],"iteration":742,"passed_time":1.12071834,"remaining_time":0.3876508928},
{"learn":[3.445646714],"iteration":743,"passed_time":1.121873908,"remaining_time":0.3860211297},
{"learn":[3.44411263],"iteration":744,"passed_time":1.123035489,"remaining_time":0.3843946977},
{"learn":[3.443264164],"iteration":745,"passed_time":1.124308678,"remaining_time":0.3828075122},
{"learn":[3.439521363],"iteration":746,"passed_time":1.125557068,"remaining_time":0.3812127685},
{"learn":[3.436809225],"iteration":747,"passed_time":1.126742354,"remaining_time":0.3795976914},
{"learn":[3.435509465],"iteration":748,"passed_time":1.127946976,"remaining_time":0.3779902418},
{"learn":[3.434450277],"iteration":749,"passed_time":1.129209475,"remaining_time":0.3764031583},
{"learn":[3.431786753],"iteration":750,"passed_time":1.130285646,"remaining_time":0.3747551609},
{"learn":[3.430150302],"iteration":751,"passed_time":1.13147086,"remaining_time":0.3731446452},
{"learn":[3.42696281],"iteration":752,"passed_time":1.132672177,"remaining_time":0.3715405416},
{"learn":[3.426870334],"iteration":753,"passed_time":1.133745131,"remaining_time":0.3698956263},
{"learn":[3.425200309],"iteration":754,"passed_time":1.134716688,"remaining_time":0.3682193227},
{"learn":[3.423383783],"iteration":755,"passed_time":1.135710558,"remaining_time":0.3665520849},
{"learn":[3.422752979],"iteration":756,"passed_time":1.136896252,"remaining_time":0.3649482024},
{"learn":[3.420845924],"iteration":757,"passed_time":1.137916116,"remaining_time":0.3632924802},
{"learn":[3.418917862],"iteration":758,"passed_time":1.13921466,"remaining_time":0.3617269211},
{"learn":[3.417095735],"iteration":759,"passed_time":1.140271669,"remaining_time":0.3600857901},
{"learn":[3.414391848],"iteration":760,"passed_time":1.141766315,"remaining_time":0.3585836391},
{"learn":[3.41426711],"iteration":761,"passed_time":1.142967504,"remaining_time":0.3569898505},
{"learn":[3.411976013],"iteration":762,"passed_time":1.144257123,"remaining_time":0.3554245586},
{"learn":[3.408614844],"iteration":763,"passed_time":1.145276184,"remaining_time":0.3537764129},
{"learn":[3.407906721],"iteration":764,"passed_time":1.146392676,"remaining_time":0.3521598415},
{"learn":[3.407494015],"iteration":765,"passed_time":1.14779616,"remaining_time":0.3506322473},
{"learn":[3.406287128],"iteration":766,"passed_time":1.14880349,"remaining_time":0.3489846327},
{"learn":[3.404600442],"iteration":767,"passed_time":1.14988525,"remaining_time":0.3473611692},
{"learn":[3.404012662],"iteration":768,"passed_time":1.151642422,"remaining_time":0.345942002},
{"learn":[3.400398762],"iteration":769,"passed_time":1.152795334,"remaining_time":0.3443414633},
{"learn":[3.399737714],"iteration":770,"passed_time":1.154007815,"remaining_time":0.3427597791},
{"learn":[3.399185251],"iteration":771,"passed_time":1.156021966,"remaining_time":0.3414158139},
{"learn":[3.397245411],"iteration":772,"passed_time":1.15758891,"remaining_time":0.3399387872},
{"learn":[3.396229831],"iteration":773,"passed_time":1.158715234,"remaining_time":0.3383328719},
{"learn":[3.394002836],"iteration":774,"passed_time":1.159813614,"remaining_time":0.3367200815},
{"learn":[3.389617243],"iteration":775,"passed_time":1.160945644,"remaining_time":0.3351183301},
{"learn":[3.385426488],"iteration":776,"passed_time":1.161967868,"remaining_time":0.3334862737},
{"learn":[3.385072258],"iteration":777,"passed_time":1.162891306,"remaining_time":0.3318275962},
{"learn":[3.383842366],"iteration":778,"passed_time":1.163996497,"remaining_time":0.3302223694},
{"learn":[3.380110746],"iteration":779,"passed_time":1.165201346,"remaining_time":0.3286465335},
{"learn":[3.378595218],"iteration":780,"passed_time":1.166381449,"remaining_time":0.3270647086},
{"learn":[3.377371219],"iteration":781,"passed_time":1.167473919,"remaining_time":0.3254594811},
{"learn":[3.375814782],"iteration":782,"passed_time":1.168441513,"remaining_time":0.3238209556},
{"learn":[3.374195887],"iteration":783,"passed_time":1.169760572,"remaining_time":0.3222809739},
{"learn":[3.373704309],"iteration":784,"passed_time":1.171038715,"remaining_time":0.3207303488},
{"learn":[3.372971757],"iteration":785,"passed_time":1.172342041,"remaining_time":0.3191872733},
{"learn":[3.371565136],"iteration":786,"passed_time":1.173700668,"remaining_time":0.3176597743},
{"learn":[3.3700309],"iteration":787,"passed_time":1.174841914,"remaining_time":0.3160742205},
{"learn":[3.368186663],"iteration":788,"passed_time":1.176637204,"remaining_time":0.3146647023},
{"learn":[3.366710398],"iteration":789,"passed_time":1.178397864,"remaining_time":0.3132450018},
{"learn":[3.364598042],"iteration":790,"passed_time":1.179737639,"remaining_time":0.311713232},
{"learn":[3.36348442],"iteration":791,"passed_time":1.180893891,"remaining_time":0.3101337492},
{"learn":[3.362001759],"iteration":792,"passed_time":1.182014271,"remaining_time":0.30854597},
{"learn":[3.361580401],"iteration":793,"passed_time":1.183026206,"remaining_time":0.3069312323},
{"learn":[3.359543675],"iteration":794,"passed_time":1.184008953,"remaining_time":0.3053104848},
{"learn":[3.35766119],"iteration":795,"passed_time":1.185729795,"remaining_time":0.3038805002},
{"learn":[3.354592969],"iteration":796,"passed_time":1.187963857,"remaining_time":0.3025805057},
{"learn":[3.350985986],"iteration":797,"passed_time":1.189019406,"remaining_time":0.3009798497},
{"learn":[3.349589624],"iteration":798,"passed_time":1.190055515,"remaining_time":0.2993756677},
{"learn":[3.349110856],"iteration":799,"passed_time":1.191097146,"remaining_time":0.2977742865},
{"learn":[3.345315441],"iteration":800,"passed_time":1.192149479,"remaining_time":0.2961769618},
{"learn":[3.34397474],"iteration":801,"passed_time":1.193327734,"remaining_time":0.2946120839},
{"learn":[3.343800902],"iteration":802,"passed_time":1.194437661,"remaining_time":0.2930314063},
{"learn":[3.342329465],"iteration":803,"passed_time":1.195619112,"remaining_time":0.2914693357},
{"learn":[3.34220347],"iteration":804,"passed_time":1.196864305,"remaining_time":0.2899236515},
{"learn":[3.341279219],"iteration":805,"passed_time":1.198270109,"remaining_time":0.2884173711},
{"learn":[3.337329521],"iteration":806,"passed_time":1.199381558,"remaining_time":0.2868409425},
{"learn":[3.336708453],"iteration":807,"passed_time":1.201060468,"remaining_time":0.2854005074},
{"learn":[3.333252703],"iteration":808,"passed_time":1.202432882,"remaining_time":0.2838871204},
{"learn":[3.332186769],"iteration":809,"passed_time":1.203818469,"remaining_time":0.2823771718},
{"learn":[3.330594851],"iteration":810,"passed_time":1.205009531,"remaining_time":0.2808221965},
{"learn":[3.327867442],"iteration":811,"passed_time":1.2061995,"remaining_time":0.2792678646},
{"learn":[3.327563111],"iteration":812,"passed_time":1.207311664,"remaining_time":0.2776965328},
{"learn":[3.326308994],"iteration":813,"passed_time":1.208348998,"remaining_time":0.2761092305},
{"learn":[3.326249879],"iteration":814,"passed_time":1.209374275,"remaining_time":0.274520541},
{"learn":[3.322336238],"iteration":815,"passed_time":1.210873816,"remaining_time":0.2730401742},
{"learn":[3.320491154],"iteration":816,"passed_time":1.212322263,"remaining_time":0.2715483159},
{"learn":[3.320434271],"iteration":817,"passed_time":1.213481519,"remaining_time":0.2699922206},
{"learn":[3.319609638],"iteration":818,"passed_time":1.214450307,"remaining_time":0.2683950007},
{"learn":[3.316182682],"iteration":819,"passed_time":1.216088932,"remaining_time":0.2669463509},
{"learn":[3.313126612],"iteration":820,"passed_time":1.217735669,"remaining_time":0.265499007},
{"learn":[3.311222803],"iteration":821,"passed_time":1.219608201,"remaining_time":0.2641000727},
{"learn":[3.309627335],"iteration":822,"passed_time":1.220959253,"remaining_time":0.2625878345},
{"learn":[3.307974895],"iteration":823,"passed_time":1.222519927,"remaining_time":0.2611207611},
{"learn":[3.307321505],"iteration":824,"passed_time":1.22426708,"remaining_time":0.2596930169},
{"learn":[3.306759087],"iteration":825,"passed_time":1.225524875,"remaining_time":0.2581614143},
{"learn":[3.30484037],"iteration":826,"passed_time":1.226808487,"remaining_time":0.2566358746},
{"learn":[3.30201994],"iteration":827,"passed_time":1.227998622,"remaining_time":0.2550915011},
{"learn":[3.299302297],"iteration":828,"passed_time":1.229469016,"remaining_time":0.2536057922},
{"learn":[3.298132671],"iteration":829,"passed_time":1.231232711,"remaining_time":0.2521801938},
{"learn":[3.296976183],"iteration":830,"passed_time":1.232918424,"remaining_time":0.2507379226},
{"learn":[3.293144745],"iteration":831,"passed_time":1.234172047,"remaining_time":0.2492078171},
{"learn":[3.290284404],"iteration":832,"passed_time":1.235244959,"remaining_time":0.2476421466},
{"learn":[3.288285745],"iteration":833,"passed_time":1.236652196,"remaining_time":0.246144202},
{"learn":[3.286662667],"iteration":834,"passed_time":1.237860772,"remaining_time":0.2446072184},
{"learn":[3.285692682],"iteration":835,"passed_time":1.239167121,"remaining_time":0.2430902008},
{"learn":[3.284565611],"iteration":836,"passed_time":1.240547763,"remaining_time":0.2415881545},
{"learn":[3.283897383],"iteration":837,"passed_time":1.241855426,"remaining_time":0.24007229},
{"learn":[3.280712855],"iteration":838,"passed_time":1.243090008,"remaining_time":0.2385428979},
{"learn":[3.280468341],"iteration":839,"passed_time":1.244337467,"remaining_time":0.2370166604},
{"learn":[3.277814895],"iteration":840,"passed_time":1.245766269,"remaining_time":0.2355253707},
{"learn":[3.276316385],"iteration":841,"passed_time":1.248026818,"remaining_time":0.2341903055},
{"learn":[3.27557063],"iteration":842,"passed_time":1.250241615,"remaining_time":0.2328445238},
{"learn":[3.27499628],"iteration":843,"passed_time":1.251603294,"remaining_time":0.2313389975},
{"learn":[3.273569958],"iteration":844,"passed_time":1.252979999,"remaining_time":0.2298365679},
{"learn":[3.269665595],"iteration":845,"passed_time":1.254311914,"remaining_time":0.2283262823},
{"learn":[3.267984685],"iteration":846,"passed_time":1.255557343,"remaining_time":0.2268007951},
{"learn":[3.267702508],"iteration":847,"passed_time":1.256827898,"remaining_time":0.2252804724},
{"learn":[3.266671924],"iteration":848,"passed_time":1.258250148,"remaining_time":0.2237877178},
{"learn":[3.265359825],"iteration":849,"passed_time":1.259534856,"remaining_time":0.222270857},
{"learn":[3.2618983],"iteration":850,"passed_time":1.261405136,"remaining_time":0.2208570684},
{"learn":[3.260456253],"iteration":851,"passed_time":1.263934003,"remaining_time":0.2195566108},
{"learn":[3.258389147],"iteration":852,"passed_time":1.266006494,"remaining_time":0.2181746244},
{"learn":[3.258108469],"iteration":853,"passed_time":1.268666456,"remaining_time":0.216891455},
{"learn":[3.256424936],"iteration":854,"passed_time":1.271999867,"remaining_time":0.2157192757},
{"learn":[3.254817983],"iteration":855,"passed_time":1.274612278,"remaining_time":0.2144207571},
{"learn":[3.253898449],"iteration":856,"passed_time":1.277566509,"remaining_time":0.2131762086},
{"learn":[3.253023652],"iteration":857,"passed_time":1.280047156,"remaining_time":0.2118492962},
{"learn":[3.252845542],"iteration":858,"passed_time":1.282796903,"remaining_time":0.2105638689},
{"learn":[3.252316026],"iteration":859,"passed_time":1.285754257,"remaining_time":0.2093088325},
{"learn":[3.24975301],"iteration":860,"passed_time":1.287305967,"remaining_time":0.2078229146},
{"learn":[3.249151075],"iteration":861,"passed_time":1.288910465,"remaining_time":0.2063452949},
{"learn":[3.246257135],"iteration":862,"passed_time":1.290410371,"remaining_time":0.2048507774},
{"learn":[3.243826471],"iteration":863,"passed_time":1.292828787,"remaining_time":0.2035008276},
{"learn":[3.243190653],"iteration":864,"passed_time":1.29410819,"remaining_time":0.2019706424},
{"learn":[3.24008797],"iteration":865,"passed_time":1.295340534,"remaining_time":0.2004337546},
{"learn":[3.240036811],"iteration":866,"passed_time":1.296816836,"remaining_time":0.1989349932},
{"learn":[3.238676314],"iteration":867,"passed_time":1.299261299,"remaining_time":0.1975835155},
{"learn":[3.237848782],"iteration":868,"passed_time":1.301825516,"remaining_time":0.196247575},
{"learn":[3.236405498],"iteration":869,"passed_time":1.303231409,"remaining_time":0.1947357278},
{"learn":[3.233378068],"iteration":870,"passed_time":1.305298733,"remaining_time":0.1933220856},
{"learn":[3.233169169],"iteration":871,"passed_time":1.306829651,"remaining_time":0.1918282056},
{"learn":[3.232434885],"iteration":872,"passed_time":1.308441661,"remaining_time":0.1903460378},
{"learn":[3.229978115],"iteration":873,"passed_time":1.309873439,"remaining_time":0.1888375897},
{"learn":[3.229648848],"iteration":874,"passed_time":1.311682906,"remaining_time":0.1873832722},
{"learn":[3.227208761],"iteration":875,"passed_time":1.314237081,"remaining_time":0.1860335593},
{"learn":[3.226258869],"iteration":876,"passed_time":1.315716307,"remaining_time":0.1845303373},
{"learn":[3.225331995],"iteration":877,"passed_time":1.317471612,"remaining_time":0.1830655315},
{"learn":[3.221968268],"iteration":878,"passed_time":1.319131706,"remaining_time":0.1815869584},
{"learn":[3.221166317],"iteration":879,"passed_time":1.321440776,"remaining_time":0.1801964694},
{"learn":[3.220047503],"iteration":880,"passed_time":1.32391153,"remaining_time":0.1788257344},
{"learn":[3.21982781],"iteration":881,"passed_time":1.326392869,"remaining_time":0.1774539212},
{"learn":[3.216693405],"iteration":882,"passed_time":1.32912854,"remaining_time":0.1761132947},
{"learn":[3.214798761],"iteration":883,"passed_time":1.331682686,"remaining_time":0.1747456919},
{"learn":[3.214395085],"iteration":884,"passed_time":1.333212785,"remaining_time":0.1732423393},
{"learn":[3.213470696],"iteration":885,"passed_time":1.334591544,"remaining_time":0.1717194538},
{"learn":[3.211595017],"iteration":886,"passed_time":1.336786836,"remaining_time":0.170300916},
{"learn":[3.210965255],"iteration":887,"passed_time":1.337981713,"remaining_time":0.1687544503},
{"learn":[3.209413583],"iteration":888,"passed_time":1.339106973,"remaining_time":0.1672000833},
{"learn":[3.208331683],"iteration":889,"passed_time":1.340241427,"remaining_time":0.1656478168},
{"learn":[3.207110711],"iteration":890,"passed_time":1.341450197,"remaining_time":0.1641055797},
{"learn":[3.204519413],"iteration":891,"passed_time":1.342579053,"remaining_time":0.1625544145},
{"learn":[3.201421296],"iteration":892,"passed_time":1.344331694,"remaining_time":0.1610789376},
{"learn":[3.200691259],"iteration":893,"passed_time":1.345643707,"remaining_time":0.1595505961},
{"learn":[3.200485067],"iteration":894,"passed_time":1.347118036,"remaining_time":0.1580417807},
{"learn":[3.197467568],"iteration":895,"passed_time":1.348679474,"remaining_time":0.1565431532},
{"learn":[3.195838544],"iteration":896,"passed_time":1.349938204,"remaining_time":0.1550096266},
{"learn":[3.195671746],"iteration":897,"passed_time":1.351971597,"remaining_time":0.1535647026},
{"learn":[3.194213094],"iteration":898,"passed_time":1.353346589,"remaining_time":0.1520445},
{"learn":[3.192884691],"iteration":899,"passed_time":1.354535169,"remaining_time":0.1505039077},
{"learn":[3.188364239],"iteration":900,"passed_time":1.355743595,"remaining_time":0.1489662774},
{"learn":[3.185219478],"iteration":901,"passed_time":1.356903565,"remaining_time":0.1474241124},
{"learn":[3.184120387],"iteration":902,"passed_time":1.3581079,"remaining_time":0.1458875596},
{"learn":[3.183725321],"iteration":903,"passed_time":1.359277616,"remaining_time":0.1443480654},
{"learn":[3.181264554],"iteration":904,"passed_time":1.360480979,"remaining_time":0.1428129205},
{"learn":[3.180741589],"iteration":905,"passed_time":1.361732912,"remaining_time":0.1412835471},
{"learn":[3.179782639],"iteration":906,"passed_time":1.362837396,"remaining_time":0.1397396668},
{"learn":[3.176377564],"iteration":907,"passed_time":1.363954361,"remaining_time":0.138198019},
{"learn":[3.174078182],"iteration":908,"passed_time":1.365109724,"remaining_time":0.1366611495},
{"learn":[3.171242379],"iteration":909,"passed_time":1.366896943,"remaining_time":0.1351876097},
{"learn":[3.170421012],"iteration":910,"passed_time":1.368342299,"remaining_time":0.1336799831},
{"learn":[3.170087224],"iteration":911,"passed_time":1.369596689,"remaining_time":0.1321540665},
{"learn":[3.167303059],"iteration":912,"passed_time":1.370610067,"remaining_time":0.1306057786},
{"learn":[3.16705966],"iteration":913,"passed_time":1.371725212,"remaining_time":0.1290682365},
{"learn":[3.165667683],"iteration":914,"passed_time":1.372555526,"remaining_time":0.1275051581},
{"learn":[3.164689733],"iteration":915,"passed_time":1.373660045,"remaining_time":0.1259688251},
{"learn":[3.163311455],"iteration":916,"passed_time":1.374903007,"remaining_time":0.1244459646},
{"learn":[3.159425016],"iteration":917,"passed_time":1.376099791,"remaining_time":0.1229195892},
{"learn":[3.159327058],"iteration":918,"passed_time":1.377267743,"remaining_time":0.1213913898},
{"learn":[3.15819426],"iteration":919,"passed_time":1.378368262,"remaining_time":0.1198581098},
{"learn":[3.157086603],"iteration":920,"passed_time":1.379483069,"remaining_time":0.1183269951},
{"learn":[3.153354154],"iteration":921,"passed_time":1.380825009,"remaining_time":0.1168159986},
{"learn":[3.153261317],"iteration":922,"passed_time":1.382412332,"remaining_time":0.1153258391},
{"learn":[3.153168454],"iteration":923,"passed_time":1.383563441,"remaining_time":0.1137995904},
{"learn":[3.152080399],"iteration":924,"passed_time":1.384824416,"remaining_time":0.1122830607},
{"learn":[3.151635144],"iteration":925,"passed_time":1.385910303,"remaining_time":0.1107530911},
{"learn":[3.147762655],"iteration":926,"passed_time":1.38694549,"remaining_time":0.1092200872},
{"learn":[3.147172317],"iteration":927,"passed_time":1.388117175,"remaining_time":0.1076987464},
{"learn":[3.146254125],"iteration":928,"passed_time":1.389201217,"remaining_time":0.1061714601},
{"learn":[3.144869828],"iteration":929,"passed_time":1.390248099,"remaining_time":0.10464233},
{"learn":[3.143466218],"iteration":930,"passed_time":1.391427168,"remaining_time":0.1031240329},
{"learn":[3.141919643],"iteration":931,"passed_time":1.392709136,"remaining_time":0.1016139713},
{"learn":[3.141054135],"iteration":932,"passed_time":1.393850108,"remaining_time":0.1000942736},
{"learn":[3.139390417],"iteration":933,"passed_time":1.395035945,"remaining_time":0.09857855718},
{"learn":[3.139025283],"iteration":934,"passed_time":1.396181138,"remaining_time":0.0970607208},
{"learn":[3.137824183],"iteration":935,"passed_time":1.397726604,"remaining_time":0.09557104984},
{"learn":[3.135620453],"iteration":936,"passed_time":1.399130389,"remaining_time":0.09407173374},
{"learn":[3.13443178],"iteration":937,"passed_time":1.400638963,"remaining_time":0.09257954768},
{"learn":[3.132765713],"iteration":938,"passed_time":1.401956594,"remaining_time":0.0910749225},
{"learn":[3.131434124],"iteration":939,"passed_time":1.402922417,"remaining_time":0.0895482394},
{"learn":[3.128384262],"iteration":940,"passed_time":1.404225637,"remaining_time":0.08804390285},
{"learn":[3.128120455],"iteration":941,"passed_time":1.405618507,"remaining_time":0.08654551317},
{"learn":[3.126314615],"iteration":942,"passed_time":1.406697582,"remaining_time":0.08502837983},
{"learn":[3.125409666],"iteration":943,"passed_time":1.407787954,"remaining_time":0.08351284475},
{"learn":[3.123072589],"iteration":944,"passed_time":1.409156431,"remaining_time":0.08201439547},
{"learn":[3.122921099],"iteration":945,"passed_time":1.410976541,"remaining_time":0.08054200129},
{"learn":[3.122182662],"iteration":946,"passed_time":1.412828426,"remaining_time":0.07907065107},
{"learn":[3.120040951],"iteration":947,"passed_time":1.414622734,"remaining_time":0.07759533982},
{"learn":[3.118767799],"iteration":948,"passed_time":1.416257237,"remaining_time":0.07611076825},
{"learn":[3.118203218],"iteration":949,"passed_time":1.418016959,"remaining_time":0.07463247153},
{"learn":[3.116343362],"iteration":950,"passed_time":1.42015947,"remaining_time":0.07317330604},
{"learn":[3.11480829],"iteration":951,"passed_time":1.421554252,"remaining_time":0.0716750043},
{"learn":[3.112607903],"iteration":952,"passed_time":1.422962236,"remaining_time":0.07017757095},
{"learn":[3.111661241],"iteration":953,"passed_time":1.424511972,"remaining_time":0.06868716007},
{"learn":[3.110249676],"iteration":954,"passed_time":1.425961142,"remaining_time":0.06719188626},
{"learn":[3.107333579],"iteration":955,"passed_time":1.427718418,"remaining_time":0.06571088951},
{"learn":[3.107149851],"iteration":956,"passed_time":1.430120093,"remaining_time":0.06425826957},
{"learn":[3.106867336],"iteration":957,"passed_time":1.432164572,"remaining_time":0.06278800838},
{"learn":[3.10364681],"iteration":958,"passed_time":1.433514392,"remaining_time":0.06128685096},
{"learn":[3.102703811],"iteration":959,"passed_time":1.434866124,"remaining_time":0.05978608849},
{"learn":[3.101469264],"iteration":960,"passed_time":1.436221186,"remaining_time":0.05828577134},
{"learn":[3.09863569],"iteration":961,"passed_time":1.437644068,"remaining_time":0.05678843511},
{"learn":[3.09645939],"iteration":962,"passed_time":1.439443925,"remaining_time":0.0553057375},
{"learn":[3.096240186],"iteration":963,"passed_time":1.441931571,"remaining_time":0.05384806695},
{"learn":[3.094838828],"iteration":964,"passed_time":1.444695455,"remaining_time":0.05239828076},
{"learn":[3.094176802],"iteration":965,"passed_time":1.446707581,"remaining_time":0.05091931445},
{"learn":[3.093182279],"iteration":966,"passed_time":1.448080372,"remaining_time":0.0494174274},
{"learn":[3.090150687],"iteration":967,"passed_time":1.449567105,"remaining_time":0.0479195737},
{"learn":[3.088612829],"iteration":968,"passed_time":1.450810286,"remaining_time":0.04641395135},
{"learn":[3.087153684],"iteration":969,"passed_time":1.452087836,"remaining_time":0.04490993308},
{"learn":[3.085866843],"iteration":970,"passed_time":1.453147657,"remaining_time":0.04339987853},
{"learn":[3.082669094],"iteration":971,"passed_time":1.454343399,"remaining_time":0.04189466582},
{"learn":[3.081047548],"iteration":972,"passed_time":1.455387612,"remaining_time":0.04038588439},
{"learn":[3.079684322],"iteration":973,"passed_time":1.456882455,"remaining_time":0.03889008606},
{"learn":[3.07613431],"iteration":974,"passed_time":1.459356333,"remaining_time":0.03741939315},
{"learn":[3.074005935],"iteration":975,"passed_time":1.461364775,"remaining_time":0.03593519938},
{"learn":[3.072988853],"iteration":976,"passed_time":1.462703394,"remaining_time":0.03443416382},
{"learn":[3.072344268],"iteration":977,"passed_time":1.463810485,"remaining_time":0.03292825221},
{"learn":[3.070654438],"iteration":978,"passed_time":1.465690434,"remaining_time":0.03143973352},
{"learn":[3.069724506],"iteration":979,"passed_time":1.467241457,"remaining_time":0.02994370321},
{"learn":[3.067763166],"iteration":980,"passed_time":1.468309072,"remaining_time":0.02843819813},
{"learn":[3.066737893],"iteration":981,"passed_time":1.46959172,"remaining_time":0.02693752644},
{"learn":[3.065248174],"iteration":982,"passed_time":1.471117074,"remaining_time":0.02544149568},
{"learn":[3.063186837],"iteration":983,"passed_time":1.472873379,"remaining_time":0.02394916064},
{"learn":[3.062880371],"iteration":984,"passed_time":1.474687874,"remaining_time":0.02245717575},
{"learn":[3.061288645],"iteration":985,"passed_time":1.476186322,"remaining_time":0.02096004919},
{"learn":[3.059970575],"iteration":986,"passed_time":1.477968171,"remaining_time":0.01946665271},
{"learn":[3.059576341],"iteration":987,"passed_time":1.479303651,"remaining_time":0.01796725082},
{"learn":[3.058175919],"iteration":988,"passed_time":1.480505728,"remaining_time":0.01646669667},
{"learn":[3.056830702],"iteration":989,"passed_time":1.482418845,"remaining_time":0.01497392772},
{"learn":[3.056336579],"iteration":990,"passed_time":1.483675723,"remaining_time":0.01347435066},
{"learn":[3.055810414],"iteration":991,"passed_time":1.48495776,"remaining_time":0.01197546581},
{"learn":[3.055476518],"iteration":992,"passed_time":1.486421853,"remaining_time":0.01047830108},
{"learn":[3.053331734],"iteration":993,"passed_time":1.488616108,"remaining_time":0.00898561031},
{"learn":[3.050890374],"iteration":994,"passed_time":1.490037477,"remaining_time":0.007487625514},
{"learn":[3.04972623],"iteration":995,"passed_time":1.491306002,"remaining_time":0.00598918073},
{"learn":[3.047217327],"iteration":996,"passed_time":1.492595665,"remaining_time":0.004491260779},
{"learn":[3.047155483],"iteration":997,"passed_time":1.494182227,"remaining_time":0.002994353161},
{"learn":[3.04430671],"iteration":998,"passed_time":1.496186489,"remaining_time":0.001497684173},
{"learn":[3.042664195],"iteration":999,"passed_time":1.498092493,"remaining_time":0}
]}